Workbook

Sheet new_jobs
A1: Unique? | B1: final_job_id | C1: platform | D1: company | E1: slug | F1: job_id | G1: title | H1: location | I1: is_remote | J1: is_hybrid | K1: url | L1: description | M1: New | N1: Rem_Hyb
A2: {=SUM((B2=$B$2:$B$127)*1)} -> 1 | B2: greenhouse|figma|5220003004 | C2: greenhouse | D2: Figma | E2: figma | F2: 5220003004 | G2: Data Engineer | H2: San Francisco, CA • New York, NY • United States | I2: 1 | J2: 0 | K2: https://boards.greenhouse.io/figma/jobs/5220003004?gh_jid=5220003004 | L2: Figma is growing our team of passionate creatives and builders on a mission to make design accessible to all. Figma’s platform helps teams bring ideas to life—whether you're brainstorming, creating a prototype, translating designs into code, or iterating with AI. From idea to product, Figma empowers teams to streamline workflows, move faster, and work together in real time from anywhere in the world. If you're excited to shape the future of design and collaboration, join us! We are looking for an experienced Data Engineer to partner with our Data Science and Data Infrastructure teams to own and scale our data pipelines. You’ll also work closely with stakeholders across business teams including sales, marketing, and finance to ensure that the data they need arrives promptly and reliably. You’ll play an integral role in building the metrics and self-serve reporting capabilities to unlock Figma’s next phase of growth. This is a great role for an individual who is passionate about working with data and data systems, and who love s solving problems. You’ll have a good sense for when it makes sense to build fast, scrappy solution s to unblock a key stakeholder vs. when to push back or bring in an outside service. The ideal candidate will be a great communicator who can help coordinate across multiple internal and external teams and take s pride in building end-to-end projects. This is a full time role that can be held from one of our US hubs or remotely in the United States. What you'll do at Figma : Own, build, and maintai n scalable data pipelines that connect various cloud data sources. Develop a deep understanding of Figma’s core data model s and optimize data pipelines for scale. Partner with the Data Science and Data Infrastructure teams to build new foundational data sets that are trusted, well understood, and enable self-service . Work with a wide range of cross-functional stakeholders to derive requirements and architect shared datasets; ability to document, simplify and explain complex problems to different types of audiences. Establish best practices for the development of specialized data sets for analytics and modeling. We'd love to hear from you if you have: 4 + years in a relevant field. Fluency with both SQL and Python. Familiarity with Snowflake, dbt, Dagster, and ETL/reverse ETL tools. Excellent judgment and creative problem solving skills. A self-starting mindset along with strong communication and collaboration skills. While not required, it’s an added plus if you also have: Knowledge in data modeling methodologies to design and build robust data architectures for insightful analytics. Experience with business systems such as Salesforce , Customer IO, Stripe, NetSuite is a big plus. At Figma, one of our values is Grow as you go. We believe in hiring smart, curious people who are excited to learn and develop their skills. If you’re excited about this role but your past experience doesn’t align perfectly with the points outlined in the job description, we encourage you to apply anyways. You may be just the right candidate for this or other roles. Pay Transparency Disclosure If based in Figma’s San Francisco or New York hub offices, this role has the annual base salary range stated below. Job level and actual compensation will be decided based on factors including, but not limited to, individual qualifications objectively assessed during the interview process (including skills and prior relevant experience, potential impact, and scope of role), market demands, and specific work location. The listed range is a guideline, and the range for this role may be modified. For roles that are available to be filled remotely, the pay range is localized according to employee work location by a factor of between 80% and 100% of range. Please discuss your specific work location with your recruiter for more information. Figma offers equity to employees, as well a competitive package of additional benefits, including health, dental & vision, retirement with company contribution, parental leave & reproductive or family planning support, mental health & wellness benefits, generous PTO, company recharge days, a learning & development stipend, a work from home stipend, and cell phone reimbursement. Figma also offers sales incentive pay for most sales roles and an annual bonus plan for eligible non-sales roles. Figma’s compensation and benefits are subject to change and may be modified in the future. Annual Base Salary Range: $140,000 — $348,000 USD At Figma we celebrate and support our differences. We know employing a team rich in diverse thoughts, experiences, and opinions allows our employees, our product and our community to flourish. Figma is an equal opportunity workplace - we are dedicated to equal employment opportunities regardless of race, color, ancestry, religion, sex, national origin, sexual orientation, age, citizenship, marital status, disability, gender identity/expression, veteran status , or any other characteristic protected by law. We also consider qualified applicants regardless of criminal histories, consistent with legal requirements. We will work to ensure individuals with disabilities are provided reasonable accommodation to apply for a role, participate in the interview process, perform essential job functions, and receive other benefits and privileges of employment. If you require accommodation, please reach out to accommodations-ext@figma.com . These modifications enable an individual with a disability to have an equal opportunity not only to get a job, but successfully perform their job tasks to the same extent as people without disabilities. Examples of accommodations include but are not limited to: Holding interviews in an accessible location Enabling closed captioning on video conferencing Ensuring all written communication be compatible with screen readers Changing the mode or format of interviews To ensure the integrity of our hiring process and facilitate a more personal connection, we require all candidates keep their cameras on during video interviews. Additionally, if hired you will be required to attend in person onboarding. By applying for this job, the candidate acknowledges and agrees that any personal data contained in their application or supporting materials will be processed in accordance with Figma's Candidate Privacy Notice . | M2: 0 | N2: =I2+J2 -> 1 | O2: {=OR(B2=Hist!$A$1:$A$85)} -> TRUE
A3: {=SUM((B3=$B$2:$B$127)*1)} -> 1 | B3: greenhouse|figma|5552580004 | C3: greenhouse | D3: Figma | E3: figma | F3: 5552580004 | G3: Data Scientist | H3: San Francisco, CA • New York, NY • United States | I3: 1 | J3: 0 | K3: https://boards.greenhouse.io/figma/jobs/5552580004?gh_jid=5552580004 | L3: Figma is growing our team of passionate creatives and builders on a mission to make design accessible to all. Figma’s platform helps teams bring ideas to life—whether you're brainstorming, creating a prototype, translating designs into code, or iterating with AI. From idea to product, Figma empowers teams to streamline workflows, move faster, and work together in real time from anywhere in the world. If you're excited to shape the future of design and collaboration, join us! We are looking for an experienced Data Scientist to join our growing data team. At Figma, Data Scientists are deeply embedded within cross-functional teams across the company—from Product to Finance, Marketing, and Platform. We are hiring across a number of roles in these areas. This is ideal for someone excited to own high-impact data projects, partner strategically with stakeholders, and shape the future of our products and business. The ideal candidate will bring strong analytical and technical skills, business intuition, and a collaborative mindset to guide decision-making and unlock growth opportunities. You’ll work on problems ranging from understanding user behavior to optimizing revenue strategies, improving internal tooling, and influencing product direction through experimentation and data modeling. This is a full-time role that can be held from one of our US hubs or remotely in the United States. What you’ll do at Figma: Collaborate across teams to define and measure key metrics, design experiments, and uncover insights that inform strategic decisions Build models and analytical frameworks to support product, marketing, platform, or finance initiatives Develop tools, datasets, and systems that enable others to work with data more efficiently and rigorously Own complex data projects end-to-end—from problem scoping to solution delivery Champion data quality, accessibility, and the democratization of data across the organization Partner with Product, Engineering, Design, Research, Sales, Marketing, or Finance to drive impact We'd love to hear from you if you have: 4+ years of experience in Analytics, Data Science, or a related field Fluency in SQL and proficiency in a scripting language like Python or R Experience with distributed data systems (e.g., Redshift, Snowflake, Presto, Hive, Spark) Strong foundation in statistical methods, experimentation, and/or forecasting A track record of working cross-functionally and communicating effectively with both technical and non-technical partners Experience supporting one or more of the following: Product, Marketing, Finance, or internal Platform/Tooling teams While it’s not required, it’s an added plus if you also have: A self-starter attitude and the ability to thrive in ambiguous and fast-paced environments At Figma, one of our values is Grow as you go. We believe in hiring smart, curious people who are excited to learn and develop their skills. If you’re excited about this role but your past experience doesn’t align perfectly with the points outlined in the job description, we encourage you to apply anyways. You may be just the right candidate for this or other roles. Pay Transparency Disclosure If based in Figma’s San Francisco or New York hub offices, this role has the annual base salary range stated below. Job level and actual compensation will be decided based on factors including, but not limited to, individual qualifications objectively assessed during the interview process (including skills and prior relevant experience, potential impact, and scope of role), market demands, and specific work location. The listed range is a guideline, and the range for this role may be modified. For roles that are available to be filled remotely, the pay range is localized according to employee work location by a factor of between 80% and 100% of range. Please discuss your specific work location with your recruiter for more information. Figma offers equity to employees, as well a competitive package of additional benefits, including health, dental & vision, retirement with company contribution, parental leave & reproductive or family planning support, mental health & wellness benefits, generous PTO, company recharge days, a learning & development stipend, a work from home stipend, and cell phone reimbursement. Figma also offers sales incentive pay for most sales roles and an annual bonus plan for eligible non-sales roles. Figma’s compensation and benefits are subject to change and may be modified in the future. Annual Base Salary Range: $140,000 — $348,000 USD At Figma we celebrate and support our differences. We know employing a team rich in diverse thoughts, experiences, and opinions allows our employees, our product and our community to flourish. Figma is an equal opportunity workplace - we are dedicated to equal employment opportunities regardless of race, color, ancestry, religion, sex, national origin, sexual orientation, age, citizenship, marital status, disability, gender identity/expression, veteran status , or any other characteristic protected by law. We also consider qualified applicants regardless of criminal histories, consistent with legal requirements. We will work to ensure individuals with disabilities are provided reasonable accommodation to apply for a role, participate in the interview process, perform essential job functions, and receive other benefits and privileges of employment. If you require accommodation, please reach out to accommodations-ext@figma.com . These modifications enable an individual with a disability to have an equal opportunity not only to get a job, but successfully perform their job tasks to the same extent as people without disabilities. Examples of accommodations include but are not limited to: Holding interviews in an accessible location Enabling closed captioning on video conferencing Ensuring all written communication be compatible with screen readers Changing the mode or format of interviews To ensure the integrity of our hiring process and facilitate a more personal connection, we require all candidates keep their cameras on during video interviews. Additionally, if hired you will be required to attend in person onboarding. By applying for this job, the candidate acknowledges and agrees that any personal data contained in their application or supporting materials will be processed in accordance with Figma's Candidate Privacy Notice . | M3: 0 | N3: =I3+J3 -> 1 | O3: {=OR(B3=Hist!$A$1:$A$85)} -> TRUE
A4: {=SUM((B4=$B$2:$B$127)*1)} -> 1 | B4: greenhouse|figma|6013304004 | C4: greenhouse | D4: Figma | E4: figma | F4: 6013304004 | G4: Data Scientist, Finance | H4: San Francisco, CA • New York, NY • United States | I4: 1 | J4: 0 | K4: https://boards.greenhouse.io/figma/jobs/6013304004?gh_jid=6013304004 | L4: Figma is growing our team of passionate creatives and builders on a mission to make design accessible to all. Figma’s platform helps teams bring ideas to life—whether you're brainstorming, creating a prototype, translating designs into code, or iterating with AI. From idea to product, Figma empowers teams to streamline workflows, move faster, and work together in real time from anywhere in the world. If you're excited to shape the future of design and collaboration, join us! Figma is growing our Finance Data Science team at a pivotal moment in the company's evolution. As a public company, the accuracy, scalability, and sophistication of our financial data systems have never been more important. At the same time, Figma's business continues to evolve through new products, AI-powered offerings, acquisitions, and emerging revenue models. We're looking for a Finance Data Scientist to help build the data foundation that powers financial reporting, forecasting, strategic decision-making, and investor communications. In this role, you'll partner closely with Strategic Finance, Accounting, Investor Relations, Engineering, Product, and Data teams to ensure our financial metrics are accurate, actionable, and trusted across the business. This is a unique opportunity to work at the intersection of finance, analytics, data engineering, and business strategy—helping shape how Figma measures and communicates its performance as the company scales. The data and systems built by this team directly support executive decision-making, public company reporting, and Figma's long-term growth strategy. This is a full time role that can be held from one of our US hubs or remotely in the United States. What you'll do at Figma: Own and improve the data models that power Figma's financial reporting, including ARR, revenue, billings, collections, and other key business metrics Build scalable reporting systems, forecasts, and analytical frameworks that support Finance, Accounting, Investor Relations, and executive leadership Drive data accuracy and completeness across month-end, quarter-end, and year-end close processes alongside Strategic Finance and Accounting teams Collaborate with Engineering, Product, GTM Systems, and Financial Systems teams to ensure the completeness and accuracy of financial data Conduct deep-dive analyses that inform strategic decisions and uncover opportunities to improve business performance Define, measure, and operationalize key financial and operational metrics Design and implement durable data solutions that balance immediate stakeholder needs with long-term scalability Serve as a trusted thought partner to Finance leaders, helping guide reporting, forecasting, and decision-making across the business We'd love to hear from you if you have: 3+ years of experience in Data Science, Analytics, Finance, Financial Systems, Data Engineering, or a related field Advanced SQL skills and strong proficiency in Python or a similar programming language Experience supporting Finance, Accounting, Strategic Finance, FP&A, Investor Relations, or other finance-focused stakeholders Demonstrated ability to translate complex data into clear, actionable business insights for non-technical stakeholders Experience working independently and driving projects from ambiguity to execution While it's not required, it's an added plus if you also have: Experience with SaaS, subscription-based, usage-based, or consumption-based business models Knowledge of accounting concepts and revenue recognition principles (ASC 606) Experience with modern analytics and data engineering tools such as DBT, Snowflake, Git, Spark, Presto, or similar technologies Experience supporting IPO readiness, public company reporting, SOX controls, audits, or other major corporate milestones Background in Strategic Finance, FP&A, Accounting, Investment Banking, Consulting, or related fields At Figma, one of our values is Grow as you go. We believe in hiring smart, curious people who are excited to learn and develop their skills. If you’re excited about this role but your past experience doesn’t align perfectly with the points outlined in the job description, we encourage you to apply anyways. You may be just the right candidate for this or other roles. Pay Transparency Disclosure If based in Figma’s San Francisco or New York hub offices, this role has the annual base salary range stated below. Job level and actual compensation will be decided based on factors including, but not limited to, individual qualifications objectively assessed during the interview process (including skills and prior relevant experience, potential impact, and scope of role), market demands, and specific work location. The listed range is a guideline, and the range for this role may be modified. For roles that are available to be filled remotely, the pay range is localized according to employee work location by a factor of between 80% and 100% of range. Please discuss your specific work location with your recruiter for more information. Figma offers equity to employees, as well a competitive package of additional benefits, including health, dental & vision, retirement with company contribution, parental leave & reproductive or family planning support, mental health & wellness benefits, generous PTO, company recharge days, a learning & development stipend, a work from home stipend, and cell phone reimbursement. Figma also offers sales incentive pay for most sales roles and an annual bonus plan for eligible non-sales roles. Figma’s compensation and benefits are subject to change and may be modified in the future. Annual Base Salary Range: $140,000 — $348,000 USD At Figma we celebrate and support our differences. We know employing a team rich in diverse thoughts, experiences, and opinions allows our employees, our product and our community to flourish. Figma is an equal opportunity workplace - we are dedicated to equal employment opportunities regardless of race, color, ancestry, religion, sex, national origin, sexual orientation, age, citizenship, marital status, disability, gender identity/expression, veteran status , or any other characteristic protected by law. We also consider qualified applicants regardless of criminal histories, consistent with legal requirements. We will work to ensure individuals with disabilities are provided reasonable accommodation to apply for a role, participate in the interview process, perform essential job functions, and receive other benefits and privileges of employment. If you require accommodation, please reach out to accommodations-ext@figma.com . These modifications enable an individual with a disability to have an equal opportunity not only to get a job, but successfully perform their job tasks to the same extent as people without disabilities. Examples of accommodations include but are not limited to: Holding interviews in an accessible location Enabling closed captioning on video conferencing Ensuring all written communication be compatible with screen readers Changing the mode or format of interviews To ensure the integrity of our hiring process and facilitate a more personal connection, we require all candidates keep their cameras on during video interviews. Additionally, if hired you will be required to attend in person onboarding. By applying for this job, the candidate acknowledges and agrees that any personal data contained in their application or supporting materials will be processed in accordance with Figma's Candidate Privacy Notice . | M4: 0 | N4: =I4+J4 -> 1 | O4: {=OR(B4=Hist!$A$1:$A$85)} -> TRUE
A5: {=SUM((B5=$B$2:$B$127)*1)} -> 1 | B5: greenhouse|figma|6013303004 | C5: greenhouse | D5: Figma | E5: figma | F5: 6013303004 | G5: Data Scientist, Marketing | H5: San Francisco, CA • New York, NY • United States | I5: 1 | J5: 0 | K5: https://boards.greenhouse.io/figma/jobs/6013303004?gh_jid=6013303004 | L5: Figma is growing our team of passionate creatives and builders on a mission to make design accessible to all. Figma’s platform helps teams bring ideas to life—whether you're brainstorming, creating a prototype, translating designs into code, or iterating with AI. From idea to product, Figma empowers teams to streamline workflows, move faster, and work together in real time from anywhere in the world. If you're excited to shape the future of design and collaboration, join us! We're looking for a Marketing Data Scientist to join Figma's Data Science team and help drive how we measure, optimize, and scale our marketing investments across the customer journey. In this role, you'll work closely with Paid Marketing, Lifecycle Marketing, Demand Generation, and Growth teams to develop measurement frameworks, improve targeting and segmentation, evaluate marketing effectiveness, and uncover insights that drive business growth. This role sits at the intersection of analytics, experimentation, and strategy. You'll work with marketing leaders to answer some of Figma's most important growth questions, including how we acquire and engage customers efficiently, which marketing investments drive incremental business impact, and how we can improve the effectiveness of our marketing programs at scale. This is a unique opportunity to shape the future of marketing measurement at Figma. You'll help build best-in-class capabilities across attribution, incrementality, experimentation, forecasting, and marketing mix modeling, while partnering with stakeholders across Marketing, Finance, Product, and Research to influence high-impact decisions and accelerate growth. What you'll do at Figma: Develop and own end-to-end measurement frameworks and attribution models to evaluate the effectiveness of Figma's marketing investments across the full funnel, channels, and regions. Partner with stakeholders across Brand Marketing, Email, Lifecycle, Demand Gen and Research teams to define success metrics, uncover insights, and drive data-informed decision making. Develop and apply statistical and machine learning models to solve key marketing challenges, including audience targeting, creative effectiveness, customer engagement, and campaign performance measurement. Assess the incremental impact of marketing investments across channels to inform budget allocation and growth strategies. Build dashboards, reporting frameworks, and analytical tools that help stakeholders understand brand performance and business impact. Translate complex analyses into clear recommendations for marketing leaders and executive stakeholders. Drive foundational improvements in data quality, measurement infrastructure, and reporting capabilities across the marketing organization. Identify new opportunities to improve marketing effectiveness and influence strategic planning through data-driven insights. We'd love to hear from you if you have: 5+ years of experience in Data Science, Marketing Analytics, or a related analytical role, supporting Marketing teams and measuring large-scale investments. Strong foundation in statistics, experimentation, causal inference, and working with survey or qualitative research data. Advanced proficiency in SQL and experience using Python, R, or similar tools to conduct analysis and build scalable measurement solutions. Demonstrated ability to communicate complex analyses clearly to senior non-technical stakeholders, with a track record of influencing decisions in cross-functional environments. While it's not required, it's an added plus if you also have: Experience with marketing mix modeling (MMM), multi-touch attribution, or incrementality testing. Familiarity with data visualization tools such as Tableau, Looker, or similar. Pay Transparency Disclosure If based in Figma’s San Francisco or New York hub offices, this role has the annual base salary range stated below. Job level and actual compensation will be decided based on factors including, but not limited to, individual qualifications objectively assessed during the interview process (including skills and prior relevant experience, potential impact, and scope of role), market demands, and specific work location. The listed range is a guideline, and the range for this role may be modified. For roles that are available to be filled remotely, the pay range is localized according to employee work location by a factor of between 80% and 100% of range. Please discuss your specific work location with your recruiter for more information. Figma offers equity to employees, as well a competitive package of additional benefits, including health, dental & vision, retirement with company contribution, parental leave & reproductive or family planning support, mental health & wellness benefits, generous PTO, company recharge days, a learning & development stipend, a work from home stipend, and cell phone reimbursement. Figma also offers sales incentive pay for most sales roles and an annual bonus plan for eligible non-sales roles. Figma’s compensation and benefits are subject to change and may be modified in the future. Annual Base Salary Range: $140,000 — $348,000 USD At Figma we celebrate and support our differences. We know employing a team rich in diverse thoughts, experiences, and opinions allows our employees, our product and our community to flourish. Figma is an equal opportunity workplace - we are dedicated to equal employment opportunities regardless of race, color, ancestry, religion, sex, national origin, sexual orientation, age, citizenship, marital status, disability, gender identity/expression, veteran status , or any other characteristic protected by law. We also consider qualified applicants regardless of criminal histories, consistent with legal requirements. We will work to ensure individuals with disabilities are provided reasonable accommodation to apply for a role, participate in the interview process, perform essential job functions, and receive other benefits and privileges of employment. If you require accommodation, please reach out to accommodations-ext@figma.com . These modifications enable an individual with a disability to have an equal opportunity not only to get a job, but successfully perform their job tasks to the same extent as people without disabilities. Examples of accommodations include but are not limited to: Holding interviews in an accessible location Enabling closed captioning on video conferencing Ensuring all written communication be compatible with screen readers Changing the mode or format of interviews To ensure the integrity of our hiring process and facilitate a more personal connection, we require all candidates keep their cameras on during video interviews. Additionally, if hired you will be required to attend in person onboarding. By applying for this job, the candidate acknowledges and agrees that any personal data contained in their application or supporting materials will be processed in accordance with Figma's Candidate Privacy Notice . | M5: 0 | N5: =I5+J5 -> 1 | O5: {=OR(B5=Hist!$A$1:$A$85)} -> TRUE
A6: {=SUM((B6=$B$2:$B$127)*1)} -> 1 | B6: greenhouse|figma|5551532004 | C6: greenhouse | D6: Figma | E6: figma | F6: 5551532004 | G6: Software Engineer, Machine Learning | H6: San Francisco, CA • New York, NY • United States | I6: 1 | J6: 0 | K6: https://boards.greenhouse.io/figma/jobs/5551532004?gh_jid=5551532004 | L6: Figma is growing our team of passionate creatives and builders on a mission to make design accessible to all. Figma’s platform helps teams bring ideas to life—whether you're brainstorming, creating a prototype, translating designs into code, or iterating with AI. From idea to product, Figma empowers teams to streamline workflows, move faster, and work together in real time from anywhere in the world. If you're excited to shape the future of design and collaboration, join us! Figma is seeking a versatile and experienced Machine Learning / AI Engineer to join our growing AI team, working at the intersection of applied machine learning, infrastructure, and product innovation. Whether you’re building intelligent search systems, crafting scalable data pipelines, or enhancing AI-powered creativity tools, your work will drive user productivity, shape new product experiences, and advance the state of AI at Figma. You’ll collaborate closely with engineers, researchers, designers, and product managers across multiple teams to deliver high-quality ML-driven features and infrastructure. This is a high-impact, cross-functional role where you’ll shape both foundational systems and user-facing capabilities. This is a full time role that can be held from one of our US hubs or remotely in the United States. What you’ll do at Figma: Design, build, and productionize ML models for Search, Discovery, Ranking, Retrieval-Augmented Generation (RAG), and generative AI features. Build and maintain scalable data pipelines to collect high-quality training and evaluation datasets, including annotation systems and human-in-the-loop workflows. Collaborate with AI researchers to iterate on datasets, evaluation metrics, and model architectures to improve quality and relevance. Work with product engineers to define and deliver impactful AI features across Figma’s platform. Partner with infrastructure engineers to develop and optimize systems for training, inference, monitoring, and deployment. Explore new ideas at the edge of what’s technically possible and help shape the long-term AI vision at Figma. We’d love to hear from you If you have: 5+ years of industry experience in software engineering, with 3+ years focused on applied machine learning or AI. Strong experience with end-to-end ML model development, including training, evaluation, deployment, and monitoring. Proficiency in Python and familiarity with ML libraries like PyTorch, TensorFlow, Scikit-learn, Spark MLlib, or XGBoost. Experience designing and building scalable data and annotation pipelines, as well as evaluation systems for AI model quality. Experience mentoring or leading others and contributing to a culture of technical excellence and innovation. While not required, It’s an added plus if you also have: Familiarity with search relevance, ranking, NLP, or RAG systems. Experience with AI infrastructure and MLOps, including observability, CI/CD, and automation for ML workflows. Experience working on creative or design-focused ML applications. Knowledge of additional languages such as C++ or Go is a plus, but not required. A product mindset with the ability to tie technical work to user outcomes and business impact. Strong collaboration and communication skills, especially when working across functions (engineering, product, research). At Figma, one of our values is Grow as you go. We believe in hiring smart, curious people who are excited to learn and develop their skills. If you’re excited about this role but your past experience doesn’t align perfectly with the points outlined in the job description, we encourage you to apply anyways. You may be just the right candidate for this or other roles. Pay Transparency Disclosure If based in Figma’s San Francisco or New York hub offices, this role has the annual base salary range stated below. Job level and actual compensation will be decided based on factors including, but not limited to, individual qualifications objectively assessed during the interview process (including skills and prior relevant experience, potential impact, and scope of role), market demands, and specific work location. The listed range is a guideline, and the range for this role may be modified. For roles that are available to be filled remotely, the pay range is localized according to employee work location by a factor of between 80% and 100% of range. Please discuss your specific work location with your recruiter for more information. Figma offers equity to employees, as well a competitive package of additional benefits, including health, dental & vision, retirement with company contribution, parental leave & reproductive or family planning support, mental health & wellness benefits, generous PTO, company recharge days, a learning & development stipend, a work from home stipend, and cell phone reimbursement. Figma also offers sales incentive pay for most sales roles and an annual bonus plan for eligible non-sales roles. Figma’s compensation and benefits are subject to change and may be modified in the future. Annual Base Salary Range: $153,000 — $376,000 USD At Figma we celebrate and support our differences. We know employing a team rich in diverse thoughts, experiences, and opinions allows our employees, our product and our community to flourish. Figma is an equal opportunity workplace - we are dedicated to equal employment opportunities regardless of race, color, ancestry, religion, sex, national origin, sexual orientation, age, citizenship, marital status, disability, gender identity/expression, veteran status , or any other characteristic protected by law. We also consider qualified applicants regardless of criminal histories, consistent with legal requirements. We will work to ensure individuals with disabilities are provided reasonable accommodation to apply for a role, participate in the interview process, perform essential job functions, and receive other benefits and privileges of employment. If you require accommodation, please reach out to accommodations-ext@figma.com . These modifications enable an individual with a disability to have an equal opportunity not only to get a job, but successfully perform their job tasks to the same extent as people without disabilities. Examples of accommodations include but are not limited to: Holding interviews in an accessible location Enabling closed captioning on video conferencing Ensuring all written communication be compatible with screen readers Changing the mode or format of interviews To ensure the integrity of our hiring process and facilitate a more personal connection, we require all candidates keep their cameras on during video interviews. Additionally, if hired you will be required to attend in person onboarding. By applying for this job, the candidate acknowledges and agrees that any personal data contained in their application or supporting materials will be processed in accordance with Figma's Candidate Privacy Notice . | M6: 0 | N6: =I6+J6 -> 1 | O6: {=OR(B6=Hist!$A$1:$A$85)} -> TRUE
A7: {=SUM((B7=$B$2:$B$127)*1)} -> 1 | B7: ashby|notion|a1216dba-e175-4a3d-b712-401c9fbdcd92 | C7: ashby | D7: Notion | E7: notion | F7: a1216dba-e175-4a3d-b712-401c9fbdcd92 | G7: Data Engineer, People Analytics | H7: San Francisco, California | I7: 1 | J7: 0 | K7: https://jobs.ashbyhq.com/notion/a1216dba-e175-4a3d-b712-401c9fbdcd92 | L7: WHO WE ARE Notion is the collaborative AI workspace where teams and agents think together https://www.youtube.com/watch?v=vkpYpWfEK5s. We're building one place where your knowledge, projects, meetings, and AI tools live side by side, so work is faster, clearer, and less fragmented. Millions of individuals, small teams, and large companies run their work on Notion. Notinos (our employees) are customer zero in bringing this future of work to life. We care about craft, building things that last, and the belief that great work is still fundamentally human. Our goal isn’t to ship the next feature. Each and every team of Notinos is working to set the standard for how humans work together in the AI era. From building a business’s system of record to making and managing AI agents to automating away the busy work, we care deeply about giving our customers more time for their life’s work. ABOUT THE ROLE As Notion scales, there is a unique opportunity to build the data foundations for People Analytics that enable better decisions around hiring, performance, compensation, and org design - while maintaining strong privacy guarantees for sensitive employee data. In this role, you will design, build, and operate scalable data systems and pipelines that power People data. Your work will ensure that employee data is reliable, secure, and production-ready, enabling both analytics and AI-driven people workflows across the company. This role can be based in either San Francisco or New York City. We work from our offices on Mondays, Tuesdays and Thursdays (our Anchor Days) because we do our best thinking and building together in person. We’re looking for someone who’s excited to work alongside the team during those days. WHAT YOU'LL ACHIEVE - Partner closely with the Chief People Officer and People leadership team to translate strategic questions into clear metrics and data products that inform workforce planning, organization design, performance reviews, compensation discussions, and executive reporting - Define and build ETL/ELT pipelines and infrastructure to ingest and standardize data from HRIS and adjacent systems such as Workday, ATS, payroll, benefits, performance platforms, creating a reliable source of truth for headcount, org structure, hiring, attrition, and talent health - Design privacy-first data architecture, including access controls, PII handling, and governance standards - Implement data quality, testing, and observability systems to ensure sensitive employee data is accurate and trustworthy - Design privacy-aware data models, transformations, semantic layers, and quality checks so sensitive employee data is accurate, timely, well-documented, and governed appropriately with role-based access controls for decision-making and makes AI-powered people tools and automations reliable enough to ship to production - Partner with People Analytics to translate ambiguous requirements into scalable datasets, dashboards, and self-serve data products that give People leaders, People Partners, and managers visibility into workforce trends while reducing manual overhead. SKILLS YOU'LL NEED TO BRING - 6+ years of experience in analytics engineering, data engineering, people analytics, or a closely related role, with a track record of building trusted datasets and systems for business decision-making - Hands-on experience working with HRIS and adjacent People systems data (for example Workday, ATS (Ashby), payroll, benefits, performance, or engagement platforms) and know how to reconcile definitions across messy, evolving source systems - Proficiency in SQL and data modeling, and can build production-grade transformations, define durable metric logic, and write performant queries against large analytical datasets - Proficiency in Python (or similar OOP languages) for building data pipelines, automation, and infrastructure - Experience designing systems with data quality, testing, monitoring, and SLAs in mind - Experience with modern data tooling and cloud warehouses such as Snowflake, dbt, Airflow, Fivetran, or similar technologies, along with strong instincts around testing, monitoring, and data quality - Excellent judgment with sensitive and confidential data, and can implement infrastructure and tooling for data privacy, access controls, governance, and thoughtful interpretation of people metrics - Effectiveness in partnering directly with the CPO, People Partners, Finance, and business leaders to turn ambiguous questions into scoped solutions and clearly communicated insights - Ability to leverage AI and agent-based tools to accelerate development, while defining guardrails for safe, production-grade data workflows NICE TO HAVES - You have worked at a fast-growing start-up, a SaaS company or are eager to contribute in such an environment (being a current Notion user would be great!) Notion is committed to providing highly competitive cash compensation, equity, and benefits. The compensation offered for this role will be based on multiple factors such as location, the role’s scope and complexity, and the candidate’s experience and expertise, and may vary from the range provided below. For roles based in San Francisco, the estimated base salary range for this role is $213,000 to $250,000 By clicking “Submit Application”, I understand and agree that Notion and its affiliates and subsidiaries will collect and process my information in accordance with Notion’s Global Recruiting Privacy Policy https://notion.notion.site/Notion-Global-Recruiting-Privacy-Policy-fc3eb4e829354a26a2bb6fd5e289b550. https://dev.notion.so/a3ce416456924276a59de91bca740028?pvs=21#LI-Onsite #LI-Onsite A NOTE ON AI You don’t need deep AI expertise for every role, but we do expect every Notino to be intellectually curious, drawn to tinkering and discovery, and excited to use AI as a real collaborator in their work. For some roles, AI fluency is a core requirement — when that’s the case, we'll say so explicitly in the qualifications. People who thrive here don’t treat AI as a novelty. They use it to think better, and make their work easier for others to build on. EQUAL OPPORTUNITY & ACCOMMODATIONS We hire talented people from a wide range of backgrounds. If you’re excited about this role but don’t meet every bullet, we still encourage you to apply. Notion is an equal opportunity employer and does not discriminate on the basis of any legally protected characteristic. Consistent with applicable law, we will consider for employment qualified applicants with arrest and conviction records. Notion provides reasonable accommodations during the application process; if you need one, please let your recruiter know. Notion is proud to be an equal opportunity employer. We do not discriminate in hiring or any employment decision based on race, color, religion, national origin, age, sex (including pregnancy, childbirth, or related medical conditions), marital status, ancestry, physical or mental disability, genetic information, veteran status, gender identity or expression, sexual orientation, or other applicable legally protected characteristic. Notion considers qualified applicants with criminal histories, consistent with applicable federal, state and local law. Notion is also committed to providing reasonable accommodations for qualified individuals with disabilities and disabled veterans in our job application procedures. If you need assistance or an accommodation due to a disability, please let your recruiter know. | M7: 0 | N7: =I7+J7 -> 1 | O7: {=OR(B7=Hist!$A$1:$A$85)} -> TRUE
A8: {=SUM((B8=$B$2:$B$127)*1)} -> 1 | B8: ashby|notion|e4229ca4-8210-4282-98ed-2071478f72aa | C8: ashby | D8: Notion | E8: notion | F8: e4229ca4-8210-4282-98ed-2071478f72aa | G8: People Analytics & Operations (Rotational Program) | H8: San Francisco, California | I8: 1 | J8: 0 | K8: https://jobs.ashbyhq.com/notion/e4229ca4-8210-4282-98ed-2071478f72aa | L8: WHO WE ARE Notion is the collaborative AI workspace where teams and agents think together https://www.youtube.com/watch?v=vkpYpWfEK5s. We're building one place where your knowledge, projects, meetings, and AI tools live side by side, so work is faster, clearer, and less fragmented. Millions of individuals, small teams, and large companies run their work on Notion. Notinos (our employees) are customer zero in bringing this future of work to life. We care about craft, building things that last, and the belief that great work is still fundamentally human. Our goal isn’t to ship the next feature. Each and every team of Notinos is working to set the standard for how humans work together in the AI era. From building a business’s system of record to making and managing AI agents to automating away the busy work, we care deeply about giving our customers more time for their life’s work. ABOUT THE ROLE: You're joining Notion's People Analytics & Operations team as part of an 18-month rotational program -- the group that builds the insights engine powering every people decision Notion makes. We look for slope over intercept. We care less about where you trained and more about what you've built. If you've ever rebuilt a broken process because it was bothering you, used AI to do something you couldn't have done alone, or found yourself reading about labor economics for fun -- you're the person we're looking for. Over 18 months, you'll rotate across people operations, people analytics, and compensation/benefits. Every rotation is real work with real ownership. On the analytics side, you'll build dashboards that land in exec review, write SQL that powers headcount models, and prototype AI-assisted workflows that help our team move faster. On the operations side, you'll run the HR engine -- managing employee lifecycle transactions in Workday, owning onboarding and offboarding coordination end-to-end, triaging and resolving employee requests, and keeping our people data clean and audit-ready. You'll be paired with a senior operator who will push your craft and raise your bar. We want someone who's hungry, high-agency, and passionate about leveraging AI to build the future of work. Not "I've used ChatGPT" native -- "I use AI every day to move faster and build smarter" native. And you don't just use Notion; you build in it. At the end of 18 months, you'll declare a focus area and move into a permanent team within the People org -- whether that's People Analytics, People Operations, Total Rewards, or staying broad as a high-impact People generalist. We're intentionally building the next generation of the People team from within. WHAT YOU'LL ACHIEVE: - Build the insights engine: Write SQL that powers our headcount, attrition, and hiring funnel dashboards. Transform raw people data from Workday and Snowflake into crisp analyses that drive real decisions. For example, you might build a model that identifies where we're losing great candidates and propose a process fix. - Run the HR operations engine: You'll learn how the ops side of the house actually works by doing it. That means executing employee lifecycle transactions in Workday (new hires, transfers, terminations), coordinating onboarding and offboarding end-to-end, triaging and resolving employee requests, supporting compliance and audit readiness, and keeping headcount and requisition data clean. For example, you might own the full ops flow for an onboarding cohort and surface process gaps that shorten time-to-productivity. - Tell the story in data: Take a messy people question and produce a clean narrative: numbers to insights to recommended decision. You'll own the analytical arc end-to-end -- from pulling the data to presenting it to senior leadership. - Prototype AI-assisted workflows: Identify manual, repetitive work across HR operations and replace it with something smarter -- automated onboarding task routing, AI-assisted ticket triage, offboarding checklists that run themselves, compliance reminders that don't require a human to send. You'll have real latitude to experiment and ship things that outlive your rotation. - Build and own our Notion workspace: You'll be the People team's Notion expert. Pages, databases, dashboards, views -- you'll build operating systems the whole team relies on. From day one, you'll be the person others come to when they want to do something in Notion they didn't know was possible. SKILLS YOU'LL NEED TO BRING: - SQL is your native language: You don't reach for SQL when you have to; you reach for it when you want to think. You can write queries that join, filter, aggregate, and transform data. You debug the wrong answer and figure out exactly why it's wrong. - Quantitatively sharp: You think in numbers. You've studied business, economics, statistics, or mathematics and it showed up in your work. Analytical storytelling -- connecting numbers to insights to decisions -- is a skill you've already started building. - High agency, high urgency: You don't wait for perfect instructions. When something's broken, you fix it. When there's ambiguity, you make a call. We look for slope over intercept -- we care more about what you've built and how fast you learn than where you trained. - AI-fluent: You use AI tools every day as a real multiplier, not a novelty. You know when Claude drafts it faster, when a formula is cleaner, and when you need to write the code yourself. Come ready to show us how you've used AI to do something you couldn't have done alone. - Notion power user: You live in Notion. You know the difference between a filtered view and a linked database. You get a little excited when you find a cleaner way to structure something. From day one, you'll be one of the most fluent Notion users on the People team. NICE TO HAVES: - Some exposure to Python -- enough to know what a loop is and when to reach for one - Familiarity with Workday, Snowflake, or similar HRIS or data warehouse tools - Prior experience in a business operations, finance, or sales operations context (internships count) Notion is committed to providing highly competitive cash compensation, equity, and benefits. The compensation offered for this role will be based on multiple factors such as location, the role’s scope and complexity, and the candidate’s experience and expertise, and may vary from the range provided below. For roles based in San Francisco, the estimated base salary range for this role is $40.87 - $59.62 hourly. By clicking “Submit Application”, I understand and agree that Notion and its affiliates and subsidiaries will collect and process my information in accordance with Notion’s Global Recruiting Privacy Policy https://notion.notion.site/Notion-Global-Recruiting-Privacy-Policy-fc3eb4e829354a26a2bb6fd5e289b550. https://dev.notion.so/a3ce416456924276a59de91bca740028?pvs=21 #LI-Onsite A NOTE ON AI You don’t need deep AI expertise for every role, but we do expect every Notino to be intellectually curious, drawn to tinkering and discovery, and excited to use AI as a real collaborator in their work. For some roles, AI fluency is a core requirement — when that’s the case, we'll say so explicitly in the qualifications. People who thrive here don’t treat AI as a novelty. They use it to think better, and make their work easier for others to build on. EQUAL OPPORTUNITY & ACCOMMODATIONS We hire talented people from a wide range of backgrounds. If you’re excited about this role but don’t meet every bullet, we still encourage you to apply. Notion is an equal opportunity employer and does not discriminate on the basis of any legally protected characteristic. Consistent with applicable law, we will consider for employment qualified applicants with arrest and conviction records. Notion provides reasonable accommodations during the application process; if you need one, please let your recruiter know. Notion is proud to be an equal opportunity employer. We do not discriminate in hiring or any employment decision based on race, color, religion, national origin, age, sex (including pregnancy, childbirth, or related medical conditions), marital status, ancestry, physical or mental disability, genetic information, veteran status, gender identity or expression, sexual orientation, or other applicable legally protected characteristic. Notion considers qualified applicants with criminal histories, consistent with applicable federal, state and local law. Notion is also committed to providing reasonable accommodations for qualified individuals with disabilities and disabled veterans in our job application procedures. If you need assistance or an accommodation due to a disability, please let your recruiter know. | M8: 0 | N8: =I8+J8 -> 1 | O8: {=OR(B8=Hist!$A$1:$A$85)} -> TRUE
A9: {=SUM((B9=$B$2:$B$127)*1)} -> 1 | B9: ashby|notion|6597b600-7781-46e6-b70a-a9af4fb2b61b | C9: ashby | D9: Notion | E9: notion | F9: 6597b600-7781-46e6-b70a-a9af4fb2b61b | G9: People Analytics Lead - Recruiting | H9: San Francisco, California | I9: 1 | J9: 0 | K9: https://jobs.ashbyhq.com/notion/6597b600-7781-46e6-b70a-a9af4fb2b61b | L9: WHO WE ARE Notion is the collaborative AI workspace where teams and agents think together https://www.youtube.com/watch?v=vkpYpWfEK5s. We're building one place where your knowledge, projects, meetings, and AI tools live side by side, so work is faster, clearer, and less fragmented. Millions of individuals, small teams, and large companies run their work on Notion. Notinos (our employees) are customer zero in bringing this future of work to life. We care about craft, building things that last, and the belief that great work is still fundamentally human. Our goal isn’t to ship the next feature. Each and every team of Notinos is working to set the standard for how humans work together in the AI era. From building a business’s system of record to making and managing AI agents to automating away the busy work, we care deeply about giving our customers more time for their life’s work. ABOUT THE ROLE: You'll be Recruiting's dedicated people analytics partner — owning the data, shaping the strategy, and in the room where decisions get made. The core of the role is building trusted recruiting analytics infrastructure (funnel + stage conversion, pipeline aging, time-to-fill, offer acceptance, sourcing channel quality, and recruiter capacity) and making it self-serve for recruiters and leaders. You’ll own the stack end-to-end — from raw data in Ashby and Snowflake to clear insights that hold up in a pipeline review. You're the person who turns workforce signals into recruiting strategy — bringing a point of view. This role may be based in either our San Francisco or New York City offices. We work from our offices on Mondays, Tuesdays and Thursdays (our Anchor Days) because we do our best thinking and building together in person. We’re looking for someone who’s excited to work alongside the team during those days. WHAT YOU'LL ACHIEVE: - Own recruiting analytics end-to-end: Build and maintain the dashboards and reporting infrastructure Recruiting leadership relies on (funnel health, conversion rates by stage, time-to-fill, offer acceptance, pipeline aging, interview/interviewer effectiveness, and recruiter capacity) — real-time, self-serve, and trusted. - Build headcount + velocity models: Translate hiring targets into pipeline math (volume needed by stage, ETA to close, roles trending behind plan) and tie it to recruiter capacity and prioritization — so leaders see issues early and know what to do about them. - Make talent data decision-grade: Define core recruiting metrics and their definitions, document them, and build toward a single source of truth the team can align on. - Bring signal to pipeline leadership reviews: Show up to pipeline reviews and QBRs with crisp analysis and a recommendation (where the bottleneck is, what changed, what to test next), not just a slide deck. - Improve the recruiting system: Use data to spot where process, calibration, or prioritization is creating drag — and partner with Recruiting and Finance to fix it. - Use AI as leverage in your first 90 days: Use AI to accelerate query iteration, metric QA, and insight narratives (e.g., draft + test SQL approaches, anomaly checks, and concise readouts) while keeping the underlying logic and definitions clean and auditable. SKILLS YOU'LL NEED TO BRING: - Proven ability to build analytics that gets used: You’ve shipped dashboards/models that teams rely on to run real weekly decisions — not one-off reports. - Strong SQL + data modeling judgment: You can write complex queries, debug data issues, and build maintainable models/pipelines that other people can trust. - Quantitative modeling for recruiting problems: You can translate hiring stages into clear funnel math and capacity views, and you know how to stress-test assumptions. - Strategic partner instincts: You anticipate the questions leaders will ask, show up with the analysis, and can say what the data implies for decisions. - AI-fluent, with good taste: You use AI as a daily multiplier (analysis, QA, drafting narratives) and know when to rely on it vs. when to go to first principles. - Build in Notion: You’re comfortable structuring knowledge and workflows in Notion (databases, views, documentation) so your work is easy for others to find, trust, and build on. Notion is committed to providing highly competitive cash compensation, equity, and benefits. The compensation offered for this role will be based on multiple factors such as location, the role’s scope and complexity, and the candidate’s experience and expertise, and may vary from the range provided below. For roles based in San Francisco or New York City, the estimated base salary range for this role is $210,000 - $260,000 per year. By clicking “Submit Application”, I understand and agree that Notion and its affiliates and subsidiaries will collect and process my information in accordance with Notion’s Global Recruiting Privacy Policy https://notion.notion.site/Notion-Global-Recruiting-Privacy-Policy-fc3eb4e829354a26a2bb6fd5e289b550?pvs=74 and NYLL 144 https://notion.notion.site/Ashby-AI-Bias-Audit-2b0efdeead05803bbbfae159ec86c528. #LI-Onsite A NOTE ON AI You don’t need deep AI expertise for every role, but we do expect every Notino to be intellectually curious, drawn to tinkering and discovery, and excited to use AI as a real collaborator in their work. For some roles, AI fluency is a core requirement — when that’s the case, we'll say so explicitly in the qualifications. People who thrive here don’t treat AI as a novelty. They use it to think better, and make their work easier for others to build on. EQUAL OPPORTUNITY & ACCOMMODATIONS We hire talented people from a wide range of backgrounds. If you’re excited about this role but don’t meet every bullet, we still encourage you to apply. Notion is an equal opportunity employer and does not discriminate on the basis of any legally protected characteristic. Consistent with applicable law, we will consider for employment qualified applicants with arrest and conviction records. Notion provides reasonable accommodations during the application process; if you need one, please let your recruiter know. Notion is proud to be an equal opportunity employer. We do not discriminate in hiring or any employment decision based on race, color, religion, national origin, age, sex (including pregnancy, childbirth, or related medical conditions), marital status, ancestry, physical or mental disability, genetic information, veteran status, gender identity or expression, sexual orientation, or other applicable legally protected characteristic. Notion considers qualified applicants with criminal histories, consistent with applicable federal, state and local law. Notion is also committed to providing reasonable accommodations for qualified individuals with disabilities and disabled veterans in our job application procedures. If you need assistance or an accommodation due to a disability, please let your recruiter know. | M9: 0 | N9: =I9+J9 -> 1 | O9: {=OR(B9=Hist!$A$1:$A$85)} -> TRUE
A10: {=SUM((B10=$B$2:$B$127)*1)} -> 1 | B10: greenhouse|databricks|8520024002 | C10: greenhouse | D10: Databricks | E10: databricks | F10: 8520024002 | G10: Solutions Architect - Financial Services (Insurance) | H10: Georgia; Illinois; Massachusetts; New York; North Carolina | I10: 0 | J10: 0 | K10: https://databricks.com/company/careers/open-positions/job?gh_jid=8520024002 | L10: FEQ327R7 While candidates in the listed location(s) are encouraged to apply for this role, exceptionally well-qualified candidates in other East Coast locations will also be considered. Mission Solutions Architects at Databricks lead the growth of the Databricks Data Intelligence Platform. As a team, we have expertise in cloud platforms, data engineering, data analytics, and data science, machine learning, and AI. As a member of our team, you will exercise and grow your expertise in those areas, using open source projects such as Apache Spark™, Delta Lake, and MLflow. This is a customer-facing role, where you will work with customers, your teammates, the product team, our post-sales team,s and partners, to identify use cases for Databricks, develop architectures and solutions using our platform, and guide customers through the implementation, to accomplish meaningful outcomes for their businesses. In this process, you will build relationships with our customers, identify and cultivate champions, and establish yourself as a trusted advisor. You will report to a Field Engineering Manager within the Financial Services team at Databricks. The impact you will have : Partner with the sales team to help customers understand how Databricks can help solve their business problems Provide technical leadership for customers to evaluate and adopt Databricks Consult on big data architecture, execute proof of concepts for strategic customer projects, and validate integrations with cloud services and other 3rd party applications Build and present reference architectures, how-tos, and demonstrate applications for customers Become an expert in, and promote open source projects (Apache Spark™, Delta Lake, MLflow, and Unity Catalog) across developer communities through meetups, conferences, and webinars Travel to meet with customers in your territory What we look for : 7+ years in a customer-facing pre-sales role, or consulting role - preferably working with big-data technologies to solve data engineering and big-data analytical challenges Experience designing and architecting distributed data systems Comfortable programming in, and debugging, at least one of: Python, SQL, Scala, Java, or R Experience working with global system integrators, consulting organizations, or financial services technology, or financial services data providers is a positive differentiator Experience building solutions with public cloud providers such as AWS, Azure, or GCP Experience with Data Engineering technologies ( Ex: Spark, Hadoop, Kafka ) Experience with Data Warehousing technologies ( Ex: SQL, OLTP/OLAP/DSS ) Undergraduate degree or higher in an engineering or mathematics discipline such as Computer Science, Applied Mathematics, Electrical Engineering, etc.) Pay Range Transparency Databricks is committed to fair and equitable compensation practices. The pay range(s) for this role is listed below and represents the expected salary range for non-commissionable roles or on-target earnings for commissionable roles. Actual compensation packages are based on several factors that are unique to each candidate, including but not limited to job-related skills, depth of experience, relevant certifications and training, and specific work location. Based on the factors above, Databricks anticipates utilizing the full width of the range. The total compensation package for this position may also include eligibility for annual performance bonus, equity, and the benefits listed above. For more information regarding which range your location is in visit our page here . Local Pay Range $180,000 — $247,500 USD About Databricks Databricks is the data and AI company. More than 10,000 organizations worldwide — including Comcast, Condé Nast, Grammarly, and over 50% of the Fortune 500 — rely on the Databricks Data Intelligence Platform to unify and democratize data, analytics and AI. Databricks is headquartered in San Francisco, with offices around the globe and was founded by the original creators of Lakehouse, Apache Spark™, Delta Lake and MLflow. To learn more, follow Databricks on Twitter , LinkedIn and Facebook . Benefits At Databricks, we strive to provide comprehensive benefits and perks that meet the needs of all of our employees. For specific details on the benefits offered in your region click here . Our Commitment to Diversity and Inclusion At Databricks, we are committed to fostering a diverse and inclusive culture where everyone can excel. We take great care to ensure that our hiring practices are inclusive and meet equal employment opportunity standards. Individuals looking for employment at Databricks are considered without regard to age, color, disability, ethnicity, family or marital status, gender identity or expression, language, national origin, physical and mental ability, political affiliation, race, religion, sexual orientation, socio-economic status, veteran status, and other protected characteristics. Compliance If access to export-controlled technology or source code is required for performance of job duties, it is within Employer's discretion whether to apply for a U.S. government license for such positions, and Employer may decline to proceed with an applicant on this basis alone. | M10: 0 | N10: =I10+J10 -> 0 | O10: {=OR(B10=Hist!$A$1:$A$85)} -> FALSE
A11: {=SUM((B11=$B$2:$B$127)*1)} -> 1 | B11: greenhouse|databricks|8570023002 | C11: greenhouse | D11: Databricks | E11: databricks | F11: 8570023002 | G11: Specialist Solutions Architect - Data Engineering & Warehousing | H11: United States | I11: 0 | J11: 0 | K11: https://databricks.com/company/careers/open-positions/job?gh_jid=8570023002 | L11: FEQ327R455 - DNB FEQ327R257 - Emerging FEQ327R204 - FinS As a Specialist Solutions Architect (SSA) - Data Engineering and Warehousing , you will guide customers through cloud data engineering transformations across a wide variety of use cases. In this customer-facing role, you will collaborate with and support Solutions Architects. This requires hands-on production experience with large-scale data engineering technologies and lakehouse architecture. The SSA teams help customers navigate evaluations and successfully plan production for their business intelligence workloads while aligning their technical roadmap with the Databricks Data Intelligence Platform. As a deep go-to expert reporting to the Specialist Field Engineering Manager, you will continue to strengthen your technical skills through mentorship, continuous learning, and internal training programs. In this role, you will establish yourself as a leader in the data engineering and warehousing specialty. The impact you will have: Provide technical leadership to guide strategic customers to successful implementations on big data projects and large-scale data warehousing workloads. Prove the value of the Databricks Intelligence Platform for customer workloads by architecting production workloads, including end-to-end pipeline load performance testing and optimization. Architect production-level data pipelines, including end-to-end pipeline load performance testing and optimization. Become a technical expert in an area such as data lake technology, big data streaming, or big data ingestion and workflows. Assist Solution Architects with more advanced aspects of the technical sale, including custom proof of concept content, estimating workload sizing, and custom architectures. Provide tutorials and training to improve community adoption (including hackathons and conference presentations). Contribute to the Databricks Community. What we look for: 5+ years of experience in a technical role with deep expertise across the following areas: Software / Data Engineering: Hands-on experience with data ingestion, streaming technologies (e.g., Spark Streaming, Kafka), performance tuning, troubleshooting, and debugging Spark or other big data solutions. Data Applications Engineering: Experience building data-driven use cases, such as risk modeling, fraud detection, and customer lifetime value (LTV). Data Warehousing: Advanced query tuning, troubleshooting, data governance, and debugging MPP data warehouses or big data solutions. Experience migrating workloads from EDW systems (e.g., traditional SQL, Redshift, Snowflake, Synapse, EMR) across OLAP & OLTP workloads. Data Observability: Experience with SIEM tools (e.g., Splunk, Elastic, Sentinel), telemetry/high-velocity log ingestion, and anomaly detection. Proven track record of maintaining, scaling, and extending production data systems to evolve with complex business needs. Deep expertise across multiple core data engineering domains, including: Designing and scaling cost-efficient, high-performance data workloads (ETL/ELT, analytics) in cloud environments. Building and migrating large-scale data pipelines, including batch, CDC (Change Data Capture), and streaming ingestion. Migrating on-premises or Hadoop-based data systems to modern cloud platforms (AWS, Azure, GCP). Developing and managing modern lakehouse and warehouse systems, including Delta Lake technologies, data modeling, governance, and BI integration. Production programming experience in SQL and at least one of the following: Python, Scala, or Java. Strong familiarity with cloud infrastructure providers (AWS, Azure, or GCP) is highly desirable. Degree or Equivalent: Bachelor's degree in Computer Science, Information Systems, Engineering, or equivalent professional experience. [Preferred] Prior customer-facing experience in a pre-sales or post-sales technical role. Ability to meet expectations for technical training and role-specific milestones within 6 months of hire. Willingness to travel up to 30% as needed. Pay Range Transparency Databricks is committed to fair and equitable compensation practices. The pay range(s) for this role is listed below and represents the expected salary range for non-commissionable roles or on-target earnings for commissionable roles. Actual compensation packages are based on several factors that are unique to each candidate, including but not limited to job-related skills, depth of experience, relevant certifications and training, and specific work location. Based on the factors above, Databricks anticipates utilizing the full width of the range. The total compensation package for this position may also include eligibility for annual performance bonus, equity, and the benefits listed above. For more information regarding which range your location is in visit our page here . Local Pay Range $180,000 — $247,500 USD About Databricks Databricks is the data and AI company. More than 10,000 organizations worldwide — including Comcast, Condé Nast, Grammarly, and over 50% of the Fortune 500 — rely on the Databricks Data Intelligence Platform to unify and democratize data, analytics and AI. Databricks is headquartered in San Francisco, with offices around the globe and was founded by the original creators of Lakehouse, Apache Spark™, Delta Lake and MLflow. To learn more, follow Databricks on Twitter , LinkedIn and Facebook . Benefits At Databricks, we strive to provide comprehensive benefits and perks that meet the needs of all of our employees. For specific details on the benefits offered in your region click here . Our Commitment to Diversity and Inclusion At Databricks, we are committed to fostering a diverse and inclusive culture where everyone can excel. We take great care to ensure that our hiring practices are inclusive and meet equal employment opportunity standards. Individuals looking for employment at Databricks are considered without regard to age, color, disability, ethnicity, family or marital status, gender identity or expression, language, national origin, physical and mental ability, political affiliation, race, religion, sexual orientation, socio-economic status, veteran status, and other protected characteristics. Compliance If access to export-controlled technology or source code is required for performance of job duties, it is within Employer's discretion whether to apply for a U.S. government license for such positions, and Employer may decline to proceed with an applicant on this basis alone. | M11: 0 | N11: =I11+J11 -> 0 | O11: {=OR(B11=Hist!$A$1:$A$85)} -> FALSE
A12: {=SUM((B12=$B$2:$B$127)*1)} -> 1 | B12: greenhouse|databricks|8568122002 | C12: greenhouse | D12: Databricks | E12: databricks | F12: 8568122002 | G12: Sr. Specialist Solutions Architect - Data Engineering & Warehousing | H12: United States | I12: 0 | J12: 0 | K12: https://databricks.com/company/careers/open-positions/job?gh_jid=8568122002 | L12: FEQ327R204 As a Sr. Specialist Solutions Architect (SSA) - Data Engineering and Warehousing , you will guide customers through cloud data engineering transformations across a wide variety of use cases. In this customer-facing role, you will collaborate with and support Solutions Architects. This requires hands-on production experience with large-scale data engineering technologies and lakehouse architecture. The SSA teams help customers navigate evaluations and successfully plan production for their business intelligence workloads while aligning their technical roadmap with the Databricks Data Intelligence Platform. As a deep go-to expert reporting to the Specialist Field Engineering Manager, you will continue to strengthen your technical skills through mentorship, continuous learning, and internal training programs. In this role, you will establish yourself as a leader in the data engineering and warehousing specialty. The impact you will have: Provide technical leadership to guide strategic customers to successful implementations on big data projects and large-scale data warehousing workloads. Prove the value of the Databricks Intelligence Platform for customer workloads by architecting production workloads, including end-to-end pipeline load performance testing and optimization. Architect production-level data pipelines, including end-to-end pipeline load performance testing and optimization. Become a technical expert in an area such as data lake technology, big data streaming, or big data ingestion and workflows. Assist Solution Architects with more advanced aspects of the technical sale, including custom proof of concept content, estimating workload sizing, and custom architectures. Provide tutorials and training to improve community adoption (including hackathons and conference presentations). Contribute to the Databricks Community. What we look for: 8+ years of experience in a technical role with deep expertise across the following areas: Software / Data Engineering: Hands-on experience with data ingestion, streaming technologies (e.g., Spark Streaming, Kafka), performance tuning, troubleshooting, and debugging Spark or other big data solutions. Data Applications Engineering: Experience building data-driven use cases, such as risk modeling, fraud detection, and customer lifetime value (LTV). Data Warehousing: Advanced query tuning, troubleshooting, data governance, and debugging MPP data warehouses or big data solutions. Experience migrating workloads from EDW systems (e.g., traditional SQL, Redshift, Snowflake, Synapse, EMR) across OLAP & OLTP workloads. Data Observability: Experience with SIEM tools (e.g., Splunk, Elastic, Sentinel), telemetry/high-velocity log ingestion, and anomaly detection. Proven track record of maintaining, scaling, and extending production data systems to evolve with complex business needs. Deep expertise across multiple core data engineering domains, including: Designing and scaling cost-efficient, high-performance data workloads (ETL/ELT, analytics) in cloud environments. Building and migrating large-scale data pipelines, including batch, CDC (Change Data Capture), and streaming ingestion. Migrating on-premises or Hadoop-based data systems to modern cloud platforms (AWS, Azure, GCP). Developing and managing modern lakehouse and warehouse systems, including Delta Lake technologies, data modeling, governance, and BI integration. Production programming experience in SQL and at least one of the following: Python, Scala, or Java. Strong familiarity with cloud infrastructure providers (AWS, Azure, or GCP) is highly desirable. Degree or Equivalent: Bachelor's degree in Computer Science, Information Systems, Engineering, or equivalent professional experience. 3+ years of customer-facing experience in a pre-sales or post-sales technical role. Ability to meet expectations for technical training and role-specific milestones within 6 months of hire. Willingness to travel up to 30% as needed. Pay Range Transparency Databricks is committed to fair and equitable compensation practices. The pay range(s) for this role is listed below and represents the expected salary range for non-commissionable roles or on-target earnings for commissionable roles. Actual compensation packages are based on several factors that are unique to each candidate, including but not limited to job-related skills, depth of experience, relevant certifications and training, and specific work location. Based on the factors above, Databricks anticipates utilizing the full width of the range. The total compensation package for this position may also include eligibility for annual performance bonus, equity, and the benefits listed above. For more information regarding which range your location is in visit our page here . Local Pay Range $219,100 — $301,300 USD About Databricks Databricks is the data and AI company. More than 10,000 organizations worldwide — including Comcast, Condé Nast, Grammarly, and over 50% of the Fortune 500 — rely on the Databricks Data Intelligence Platform to unify and democratize data, analytics and AI. Databricks is headquartered in San Francisco, with offices around the globe and was founded by the original creators of Lakehouse, Apache Spark™, Delta Lake and MLflow. To learn more, follow Databricks on Twitter , LinkedIn and Facebook . Benefits At Databricks, we strive to provide comprehensive benefits and perks that meet the needs of all of our employees. For specific details on the benefits offered in your region click here . Our Commitment to Diversity and Inclusion At Databricks, we are committed to fostering a diverse and inclusive culture where everyone can excel. We take great care to ensure that our hiring practices are inclusive and meet equal employment opportunity standards. Individuals looking for employment at Databricks are considered without regard to age, color, disability, ethnicity, family or marital status, gender identity or expression, language, national origin, physical and mental ability, political affiliation, race, religion, sexual orientation, socio-economic status, veteran status, and other protected characteristics. Compliance If access to export-controlled technology or source code is required for performance of job duties, it is within Employer's discretion whether to apply for a U.S. government license for such positions, and Employer may decline to proceed with an applicant on this basis alone. | M12: 0 | N12: =I12+J12 -> 0 | O12: {=OR(B12=Hist!$A$1:$A$85)} -> FALSE
A13: {=SUM((B13=$B$2:$B$127)*1)} -> 1 | B13: greenhouse|stripe|7540441 | C13: greenhouse | D13: Stripe | E13: stripe | F13: 7540441 | G13: Credit Risk Analyst Commercial Underwriter, West Coast | H13: Chicago, US-Remote, Canada-Remote | I13: 1 | J13: 0 | K13: https://stripe.com/jobs/search?gh_jid=7540441 | L13: Who we are About Stripe Stripe is a financial infrastructure platform for businesses. Millions of companies—from the world's largest enterprises to the most ambitious startups—use Stripe to accept payments, grow their revenue, and accelerate new business opportunities. Our mission is to increase the GDP of the internet, and we have a staggering amount of work ahead. That means you have an unprecedented opportunity to put the global economy within everyone's reach while doing the most important work of your career. About the team The Credit team protects Stripe by managing the end-to-end risk of our largest and most complex users. We leverage deep underwriting expertise and data-driven stress heuristics to make informed decisions at every stage of the user lifecycle—from onboarding to loss recovery. Our goal is to enable Stripe's growth by making confident, calibrated decisions on our highest-exposure users. What you’ll do Stripe handles billions of dollars every year for businesses around the world, and the Risk team plays a critical role in the company's financial and partnership success. As a Credit Risk Analyst Commercial Underwriter on the North America Strategy Risk team, you'll underwrite and manage a portfolio of our largest and fastest-growing businesses to facilitate growth objectives while minimizing credit risk. This is a high-impact role that involves strong cross-functional partnership with Sales, Legal, Treasury, and Finance. This role is assigned to West Coast hours, with a high preference for candidates in the Pacific time zone. Responsibilities Work directly with our top merchants, from successful venture-backed startups to well-established institutions, to evaluate their business models and financial statements Provide tailored credit risk recommendations that mitigate Stripe exposure, while facilitating partner company growth Help manage the portfolio by developing a deep understanding of risk across industries, geographies, and operating models Deliver insights to support senior management decisions, ranging from onboarding strategies to merchant pricing analysis Support the refinement of tools and processes to help the team deliver on key performance indicators, such as credit loss targets or portfolio coverage metrics Work with internal and external partners to support merchants around the world Who you are We're looking for someone who meets the minimum requirements to be considered for the role. If you meet these requirements, you are encouraged to apply. The preferred qualifications are a bonus, not a requirement. Minimum requirements 5+ years of relevant experience with knowledge of commercial credit underwriting, financial risk modeling, and cash flow forecasting Bachelor's degree in Finance, Economics, Statistics, or other related fields Strong knowledge of accounting principles and comfort evaluating financial statements and business models across a range of industries Ability to transform business and financial data into cohesive narratives that outline potential credit risks and present dynamic mitigation strategies Strong written, verbal, and problem-solving skills Attention to detail while managing priorities in a fast-paced environment Ability to comfortably interact with the CFOs and CEOs of our top merchants Deep empathy for entrepreneurs running a business, and motivation to solve problems to empower them Preferred qualifications Strong technical expertise, including demonstrated experience with SQL Strong data visualization skills and a passion for data and analysis Experience working in tech, or other fast-paced, high-growth environments | M13: 0 | N13: =I13+J13 -> 1 | O13: {=OR(B13=Hist!$A$1:$A$85)} -> TRUE
... A21: {=SUM((B21=$B$2:$B$127)*1)} -> 1 | B21: greenhouse|stripe|7921649 | C21: greenhouse | D21: Stripe | E21: stripe | F21: 7921649 | G21: Staff Data Analyst | H21: US | I21: 0 | J21: 0 | K21: https://stripe.com/jobs/search?gh_jid=7921649 | L21: Who we are About Stripe Stripe is a financial infrastructure platform for businesses. Millions of companies—from the world’s largest enterprises to the most ambitious startups—use Stripe to accept payments, grow their revenue, and accelerate new business opportunities. Our mission is to increase the GDP of the internet, and we have a staggering amount of work ahead. That means you have an unprecedented opportunity to put the global economy within everyone’s reach while doing the most important work of your career. About the team The Risk Data Science team builds the data foundations, models, and measurement frameworks that power Stripe's risk and product decisions — from underwriting and reserves to merchant interventions and enablements. We're at an inflection point: as Stripe increasingly offers risk capabilities as a product to platforms and users, we need a data leader to shape how we build, measure, and evolve our risk data strategy across the What you’ll do We are looking for an experienced data analyst to drive the data strategy for our risk as a product offering. Define the metrics, data products, and analytical frameworks needed as Stripe brings risk capabilities to platforms and connected accounts at scale. Partner with Product, Engineering, and Risk leadership to ensure data investments align with the product roadmap. You will design metrics, pipelines, and data products that serve as the analytical backbone for risk decisioning. You will own the definition, reliability, and visibility of our most important risk metrics. Establish a canonical set of north star and operational metrics and ensure they are trustworthy, well-documented, and consistently surfaced to the right audiences. Build and maintain the infrastructure that keeps these metrics accurate as our data and product landscape evolves, including clear ownership, alerting on regressions, and scalable pipelines that reduce the cost of keeping insights current. You will also own and evolve Stripe's risk experimentation strategy by defining what we test, how we measure, and how we learn. Ensure we can rigorously evaluate the impact of changes to risk policies, merchant journeys, and risk models across diverse merchant populations. Finally, you will mentor and raise the bar for the Data Analysts on the team. Set technical and strategic standards. Guide junior and senior analysts on how to frame ambiguous problems, structure analyses for maximum impact, and communicate findings to senior stakeholders. Who you are We’re looking for someone who meets the minimum requirements to be considered for the role. If you meet these requirements, you are encouraged to apply. The preferred qualifications are a bonus, not a requirement. Minimum requirements 10+ years in Data Analytics, Data Science, or related roles Track record of defining and driving data strategy across multiple teams — not just executing on a roadmap, but shaping it Experience designing experimentation frameworks or measurement strategies for complex, multi-variant systems (e.g., risk policies, pricing, marketplace dynamics) Deep expertise in SQL; proficiency in Python Strong ability to translate ambiguous business problems into structured analytical approaches and communicate findings to executive stakeholders Experience building and scaling data products (metrics frameworks, pipelines, dashboards) that become operational infrastructure, not one-off analyses Demonstrated ability to influence without authority across engineering, product, and business teams Proficiency with AI tools to accelerate model development, analysis and coding Preferred qualifications Master’s degree in Mathematics, Statistics, Economics, Engineering, or a related technical field Experience in risk, trust & safety, or related domains and understanding of risk in the Fintech space Experience building data for platform/product offerings where data is part of the product surface, not just internal analytics Familiarity with causal inference and A/B testing in non-standard environments (e.g., where randomization is constrained by risk considerations) | M21: 0 | N21: =I21+J21 -> 0 | O21: {=OR(B21=Hist!$A$1:$A$85)} -> FALSE
A22: {=SUM((B22=$B$2:$B$127)*1)} -> 1 | B22: workday|usaa|/job/san-antonio-home-office-iiiii/data-scientist-lead---ai-ml_r0115805 | C22: workday | D22: USAA | E22: usaa/wd1/USAAJOBSWD | F22: /job/San-Antonio-Home-Office-IIIII/Data-Scientist-Lead---AI-ML_R0115805 | G22: Data Scientist Lead - Model Development | H22: 6 Locations | I22: 0 | J22: 0 | K22: https://usaa.wd1.myworkdayjobs.com/en-US/USAAJOBSWD/job/San-Antonio-Home-Office-IIIII/Data-Scientist-Lead---AI-ML_R0115805 | M22: 0 | N22: =I22+J22 -> 0 | O22: {=OR(B22=Hist!$A$1:$A$85)} -> FALSE
A23: {=SUM((B23=$B$2:$B$127)*1)} -> 1 | B23: workday|usaa|/job/san-antonio-home-office-i/p-c-analytics-product-development-manager--auto-telematics-_r0119126 | C23: workday | D23: USAA | E23: usaa/wd1/USAAJOBSWD | F23: /job/San-Antonio-Home-Office-I/P-C-Analytics-Product-Development-Manager--Auto-Telematics-_R0119126 | G23: P&C Analytics Product Development Manager (Auto Telematics) | H23: 6 Locations | I23: 0 | J23: 0 | K23: https://usaa.wd1.myworkdayjobs.com/en-US/USAAJOBSWD/job/San-Antonio-Home-Office-I/P-C-Analytics-Product-Development-Manager--Auto-Telematics-_R0119126 | M23: 0 | N23: =I23+J23 -> 0 | O23: {=OR(B23=Hist!$A$1:$A$85)} -> FALSE
A24: {=SUM((B24=$B$2:$B$127)*1)} -> 1 | B24: workday|usaa|/job/san-antonio-home-office-i/director--decision-science-analytics_r0117151 | C24: workday | D24: USAA | E24: usaa/wd1/USAAJOBSWD | F24: /job/San-Antonio-Home-Office-I/Director--Decision-Science-Analytics_R0117151 | G24: Director, Decision Science Analytics | H24: 6 Locations | I24: 0 | J24: 0 | K24: https://usaa.wd1.myworkdayjobs.com/en-US/USAAJOBSWD/job/San-Antonio-Home-Office-I/Director--Decision-Science-Analytics_R0117151 | M24: 0 | N24: =I24+J24 -> 0 | O24: {=OR(B24=Hist!$A$1:$A$85)} -> FALSE
A25: {=SUM((B25=$B$2:$B$127)*1)} -> 1 | B25: workday|usaa|/job/san-antonio-home-office-i/director--decision-science-analytics---omni-channel---digital-claims-analytics_r0118626 | C25: workday | D25: USAA | E25: usaa/wd1/USAAJOBSWD | F25: /job/San-Antonio-Home-Office-I/Director--Decision-Science-Analytics---Omni-Channel---Digital-Claims-Analytics_R0118626 | G25: Director, Decision Science Analytics – Omni Channel & Digital Claims Analytics | H25: 7 Locations | I25: 0 | J25: 0 | K25: https://usaa.wd1.myworkdayjobs.com/en-US/USAAJOBSWD/job/San-Antonio-Home-Office-I/Director--Decision-Science-Analytics---Omni-Channel---Digital-Claims-Analytics_R0118626 | M25: 0 | N25: =I25+J25 -> 0 | O25: {=OR(B25=Hist!$A$1:$A$85)} -> FALSE
A26: {=SUM((B26=$B$2:$B$127)*1)} -> 1 | B26: workday|usaa|/job/san-antonio-home-office-i/actuarial-analyst-ii--intermediate----forecasting-analytics_r0118072 | C26: workday | D26: USAA | E26: usaa/wd1/USAAJOBSWD | F26: /job/San-Antonio-Home-Office-I/Actuarial-Analyst-II--Intermediate----Forecasting-Analytics_R0118072 | G26: Actuarial Analyst II (Intermediate) – Forecasting Analytics | H26: 7 Locations | I26: 0 | J26: 0 | K26: https://usaa.wd1.myworkdayjobs.com/en-US/USAAJOBSWD/job/San-Antonio-Home-Office-I/Actuarial-Analyst-II--Intermediate----Forecasting-Analytics_R0118072 | M26: 0 | N26: =I26+J26 -> 0 | O26: {=OR(B26=Hist!$A$1:$A$85)} -> FALSE
A27: {=SUM((B27=$B$2:$B$127)*1)} -> 1 | B27: workday|usaa|/job/san-antonio-home-office-i/licensed-p-c-insurance-professional---sales-and-service--signing-bonus-_r0117154 | C27: workday | D27: USAA | E27: usaa/wd1/USAAJOBSWD | F27: /job/San-Antonio-Home-Office-I/Licensed-P-C-Insurance-Professional---Sales-and-Service--Signing-Bonus-_R0117154 | G27: Licensed P&C Insurance Professional - Sales and Service (Signing Bonus) | H27: San Antonio Home Office I | I27: 0 | J27: 0 | K27: https://usaa.wd1.myworkdayjobs.com/en-US/USAAJOBSWD/job/San-Antonio-Home-Office-I/Licensed-P-C-Insurance-Professional---Sales-and-Service--Signing-Bonus-_R0117154 | M27: 0 | N27: =I27+J27 -> 0 | O27: {=OR(B27=Hist!$A$1:$A$85)} -> FALSE
A28: {=SUM((B28=$B$2:$B$127)*1)} -> 1 | B28: workday|usaa|/job/san-antonio-home-office-i/insurance-professional---sales-and-service_r0117155 | C28: workday | D28: USAA | E28: usaa/wd1/USAAJOBSWD | F28: /job/San-Antonio-Home-Office-I/Insurance-Professional---Sales-and-Service_R0117155 | G28: Insurance Professional – Sales and Service | H28: San Antonio Home Office I | I28: 0 | J28: 0 | K28: https://usaa.wd1.myworkdayjobs.com/en-US/USAAJOBSWD/job/San-Antonio-Home-Office-I/Insurance-Professional---Sales-and-Service_R0117155 | M28: 0 | N28: =I28+J28 -> 0 | O28: {=OR(B28=Hist!$A$1:$A$85)} -> FALSE
A29: {=SUM((B29=$B$2:$B$127)*1)} -> 1 | B29: workday|usaa|/job/san-antonio-home-office-i/climate-scientist-senior---p-c-climate-risk---exposure-analytics_r0118347 | C29: workday | D29: USAA | E29: usaa/wd1/USAAJOBSWD | F29: /job/San-Antonio-Home-Office-I/Climate-Scientist-Senior---P-C-Climate-Risk---Exposure-Analytics_R0118347 | G29: Climate Scientist Senior – P&C Climate Risk & Exposure Analytics | H29: San Antonio Home Office I | I29: 0 | J29: 0 | K29: https://usaa.wd1.myworkdayjobs.com/en-US/USAAJOBSWD/job/San-Antonio-Home-Office-I/Climate-Scientist-Senior---P-C-Climate-Risk---Exposure-Analytics_R0118347 | M29: 0 | N29: =I29+J29 -> 0 | O29: {=OR(B29=Hist!$A$1:$A$85)} -> FALSE
A30: {=SUM((B30=$B$2:$B$127)*1)} -> 1 | B30: workday|usaa|/job/san-antonio-home-office-i/lead-graph-data-scientist---identity-analytics_r0118883 | C30: workday | D30: USAA | E30: usaa/wd1/USAAJOBSWD | F30: /job/San-Antonio-Home-Office-I/Lead-Graph-Data-Scientist---Identity-Analytics_R0118883 | G30: Lead Graph Data Scientist - Identity Analytics | H30: 6 Locations | I30: 0 | J30: 0 | K30: https://usaa.wd1.myworkdayjobs.com/en-US/USAAJOBSWD/job/San-Antonio-Home-Office-I/Lead-Graph-Data-Scientist---Identity-Analytics_R0118883 | M30: 0 | N30: =I30+J30 -> 0 | O30: {=OR(B30=Hist!$A$1:$A$85)} -> FALSE
A31: {=SUM((B31=$B$2:$B$127)*1)} -> 1 | B31: workday|usaa|/job/san-antonio-home-office-i/data-scientist-senior_r0118568 | C31: workday | D31: USAA | E31: usaa/wd1/USAAJOBSWD | F31: /job/San-Antonio-Home-Office-I/Data-Scientist-Senior_R0118568 | G31: Data Scientist Senior | H31: 6 Locations | I31: 0 | J31: 0 | K31: https://usaa.wd1.myworkdayjobs.com/en-US/USAAJOBSWD/job/San-Antonio-Home-Office-I/Data-Scientist-Senior_R0118568 | M31: 0 | N31: =I31+J31 -> 0 | O31: {=OR(B31=Hist!$A$1:$A$85)} -> FALSE
A32: {=SUM((B32=$B$2:$B$127)*1)} -> 1 | B32: workday|usaa|/job/tampa-crosstown/licensed-p-c-insurance-professional---sales-and-service--signing-bonus-_r0117494 | C32: workday | D32: USAA | E32: usaa/wd1/USAAJOBSWD | F32: /job/Tampa-Crosstown/Licensed-P-C-Insurance-Professional---Sales-and-Service--Signing-Bonus-_R0117494 | G32: Licensed P&C Insurance Professional - Sales and Service (Signing Bonus) | H32: 2 Locations | I32: 0 | J32: 0 | K32: https://usaa.wd1.myworkdayjobs.com/en-US/USAAJOBSWD/job/Tampa-Crosstown/Licensed-P-C-Insurance-Professional---Sales-and-Service--Signing-Bonus-_R0117494 | M32: 0 | N32: =I32+J32 -> 0 | O32: {=OR(B32=Hist!$A$1:$A$85)} -> FALSE
A33: {=SUM((B33=$B$2:$B$127)*1)} -> 1 | B33: workday|usaa|/job/tampa-crosstown/insurance-professional---sales-and-service_r0117484 | C33: workday | D33: USAA | E33: usaa/wd1/USAAJOBSWD | F33: /job/Tampa-Crosstown/Insurance-Professional---Sales-and-Service_R0117484 | G33: Insurance Professional - Sales and Service | H33: 2 Locations | I33: 0 | J33: 0 | K33: https://usaa.wd1.myworkdayjobs.com/en-US/USAAJOBSWD/job/Tampa-Crosstown/Insurance-Professional---Sales-and-Service_R0117484 | M33: 0 | N33: =I33+J33 -> 0 | O33: {=OR(B33=Hist!$A$1:$A$85)} -> FALSE
... A51: {=SUM((B51=$B$2:$B$127)*1)} -> 1 | B51: workday|prog leasing|/job/utah/data-scientist--remote-_jr101816-1 | C51: workday | D51: Prog Leasing | E51: progleasing/wd5/ProgLeasingCareers | F51: /job/Utah/Data-Scientist--Remote-_JR101816-1 | G51: Data Scientist (Remote) | H51: Utah | I51: 1 | J51: 0 | K51: https://progleasing.wd5.myworkdayjobs.com/en-US/ProgLeasingCareers/job/Utah/Data-Scientist--Remote-_JR101816-1 | M51: 0 | N51: =I51+J51 -> 1 | O51: {=OR(B51=Hist!$A$1:$A$85)} -> TRUE
A52: {=SUM((B52=$B$2:$B$127)*1)} -> 1 | B52: workday|prog leasing|/job/senior-data-analyst--hybrid---atlanta--ha-_jr101798 | C52: workday | D52: Prog Leasing | E52: progleasing/wd5/ProgLeasingCareers | F52: /job/Senior-Data-Analyst--Hybrid---Atlanta--HA-_JR101798 | G52: Senior Data Analyst (Hybrid - Atlanta, GA) | I52: 0 | J52: 1 | K52: https://progleasing.wd5.myworkdayjobs.com/en-US/ProgLeasingCareers/job/Senior-Data-Analyst--Hybrid---Atlanta--HA-_JR101798 | M52: 0 | N52: =I52+J52 -> 1 | O52: {=OR(B52=Hist!$A$1:$A$85)} -> TRUE
A53: {=SUM((B53=$B$2:$B$127)*1)} -> 1 | B53: workday|trinity health|/job/saint-agnes-medical-center---fresno-california/business-intelligence-analyst-lean-six-sigma-advisor_00680092 | C53: workday | D53: Trinity Health | E53: trinityhealth/wd1/Jobs | F53: /job/Saint-Agnes-Medical-Center---Fresno-California/Business-Intelligence-Analyst-Lean-Six-Sigma-Advisor_00680092 | G53: Business Intelligence Analyst/Lean Six Sigma Advisor | H53: Saint Agnes Medical Center - Fresno, California | I53: 0 | J53: 0 | K53: https://trinityhealth.wd1.myworkdayjobs.com/en-US/Jobs/job/Saint-Agnes-Medical-Center---Fresno-California/Business-Intelligence-Analyst-Lean-Six-Sigma-Advisor_00680092 | M53: 0 | N53: =I53+J53 -> 0 | O53: {=OR(B53=Hist!$A$1:$A$85)} -> FALSE
A54: {=SUM((B54=$B$2:$B$127)*1)} -> 3 | B54: workday|allstate|/job/remote---remote/business-intelligence-and-data-analytics-consultant-ii---remote_r32407 | C54: workday | D54: Allstate | E54: allstate/wd5/allstate_careers | F54: /job/Remote---Remote/Business-Intelligence-and-Data-Analytics-Consultant-II---Remote_R32407 | G54: Business Intelligence and Data Analytics Consultant II - Remote | H54: Remote - Remote | I54: 1 | J54: 0 | K54: https://allstate.wd5.myworkdayjobs.com/en-US/allstate_careers/job/Remote---Remote/Business-Intelligence-and-Data-Analytics-Consultant-II---Remote_R32407 | M54: 0 | N54: =I54+J54 -> 1 | O54: {=OR(B54=Hist!$A$1:$A$85)} -> TRUE
A55: {=SUM((B55=$B$2:$B$127)*1)} -> 3 | B55: workday|allstate|/job/remote---remote/business-intelligence-and-data-analytics-consultant-ii---remote_r32407 | C55: workday | D55: Allstate | E55: allstate/wd5/allstate_careers | F55: /job/Remote---Remote/Business-Intelligence-and-Data-Analytics-Consultant-II---Remote_R32407 | G55: Business Intelligence and Data Analytics Consultant II - Remote | H55: Remote - Remote | I55: 1 | J55: 0 | K55: https://allstate.wd5.myworkdayjobs.com/en-US/allstate_careers/job/Remote---Remote/Business-Intelligence-and-Data-Analytics-Consultant-II---Remote_R32407 | M55: 0 | N55: =I55+J55 -> 1 | O55: {=OR(B55=Hist!$A$1:$A$85)} -> TRUE
A56: {=SUM((B56=$B$2:$B$127)*1)} -> 1 | B56: greenhouse|mongodb|7696633 | C56: greenhouse | D56: MongoDB | E56: mongodb | F56: 7696633 | G56: Senior Data Analyst | H56: United States | I56: 0 | J56: 0 | K56: https://www.mongodb.com/careers/job/?gh_jid=7696633 | L56: The worldwide data management software market is massive (According to IDC, the worldwide database software market, which it refers to as the database management systems software market, was forecasted to be approximately $82 billion in 2023 growing to approximately $137 billion in 2027. This represents a 14% compound annual growth rate). At MongoDB we are transforming industries and empowering developers to build amazing apps that people use every day. We are the leading developer data platform and the first database provider to IPO in over 20 years. Join our team and be at the forefront of innovation and creativity. MongoDB is seeking a Senior Analyst to support data-driven, people-focused decision making for the company. Partnering with our People team, you will transform HR and organizational data into actionable insights to help us hire the right talent, manage our overall workforce, and improve workforce effectiveness, leading to better outcomes for our people and the company. This position requires someone with strong analytical and technical skills, the ability to tell a story with data, and who is comfortable working across multiple functional areas in a fast-paced, challenging environment. Responsibilities Partner with People teams (business partners, recruiting, culture/talent/development, etc.) to understand their questions, turn analyses into actionable data-driven insights, and make business recommendations Help develop and execute against roadmap for people data investments to both capture near-term value and set up the team for long-term success Leverage understanding of statistics to conduct analyses that help People teams make quicker, more informed decisions Write and maintain complex queries to conduct deep-dive analyses on the impact that People initiatives have on employee engagement, productivity and retention Liaise with Data Engineering and HRIS teams to create and manage a curated central repository for people data Design and build automated dashboards to empower stakeholders to self-serve their data and analytical needs Prioritize and triage analytical and reporting asks from across the People team Develop and support ongoing data governance and data quality processes Effectively communicate analytical findings to non-technical audiences Requirements 3+ years of hands-on analytics experience (focus on people/HR analytics preferred) Advanced SQL skills, comfortable manipulating very large datasets Proficient in Python or R with a strong focus on data wrangling and data analysis Extensive experience with Tableau or another leading visualization tool is required Experience analyzing complex people data (e.g. headcount, attrition, recruiting metrics, compensation data) strongly preferred but not required Experience in survey design and analysis preferred Familiarity with data architecture fundamentals and data warehousing Proficiency with data modeling and data quality best practices Demonstrated ability to effectively communicate and set priorities with key stakeholders at all levels of the organization Highly collaborative and organized, with a strong attention to detail Comfort with ambiguity and ability to work in a self-guided manner Committed to contributing to a collaborative, enjoyable, and psychologically safe work environment Exposure to Modern Cloud Data Warehouses preferred About MongoDB MongoDB is built for change, empowering our customers and our people to innovate at the speed of the market. We have redefined the database for the AI era, enabling innovators to create, transform, and disrupt industries with software. MongoDB’s unified database platform, the most widely available, globally distributed database on the market, helps organizations modernize legacy workloads, embrace innovation, and unleash AI. Our cloud-native platform, MongoDB Atlas, is the only globally distributed, multi-cloud database and is available across AWS, Google Cloud, and Microsoft Azure. With offices worldwide and over 60,000 customers, including 75% of the Fortune 100 and AI-native startups, relying on MongoDB for their most important applications, we’re powering the next era of software. Our compass at MongoDB is our Leadership Commitment, guiding how and why we make decisions, show up for each other, and win. It’s what makes us MongoDB. To drive the personal growth and business impact of our employees, we’re committed to developing a supportive and enriching culture for everyone. From employee affinity groups, to fertility assistance and a generous parental leave policy , we value our employees’ wellbeing and want to support them along every step of their professional and personal journeys. Learn more about what it’s like to work at MongoDB , and help us make an impact on the world! MongoDB is committed to providing any necessary accommodations for individuals with disabilities within our application and interview process. To request an accommodation due to a disability, please inform your recruiter. MongoDB, Inc. provides equal employment opportunities to all employees and applicants for employment and prohibits discrimination and harassment of any type and makes all hiring decisions without regard to race, color, religion, age, sex, national origin, disability status, genetics, protected veteran status, sexual orientation, gender identity or expression, or any other characteristic protected by federal, state or local laws. Req. ID: 1273383451 MongoDB’s base salary range for this role is posted below. Compensation at the time of offer is unique to each candidate and based on a variety of factors such as skill set, experience, qualifications, and work location. Salary is one part of MongoDB’s total compensation and benefits package. Other benefits for eligible employees may include: equity, participation in the employee stock purchase program, flexible paid time off, 20 weeks fully-paid gender-neutral parental leave, fertility and adoption assistance, 401(k) plan, mental health counseling, access to transgender-inclusive health insurance coverage, and health benefits offerings. Please note, the base salary range listed below and the benefits in this paragraph are only applicable to U.S.-based candidates. MongoDB’s base salary range for this role in the U.S. is: $83,000 — $162,000 USD | M56: 0 | N56: =I56+J56 -> 0 | O56: {=OR(B56=Hist!$A$1:$A$85)} -> FALSE
A57: {=SUM((B57=$B$2:$B$127)*1)} -> 1 | B57: greenhouse|mongodb|7742875 | C57: greenhouse | D57: MongoDB | E57: mongodb | F57: 7742875 | G57: Senior Python Engineer | H57: United States | I57: 0 | J57: 0 | K57: https://www.mongodb.com/careers/job/?gh_jid=7742875 | L57: Our Database Experience (DBX) Team A great MongoDB experience starts with great tools. The Database Experience team builds the libraries and tools that developers use day-to-day working with MongoDB. Our mission is to increase developer adoption, satisfaction and retention by providing a reliable, enjoyable interface for developers and other end-users. Our senior engineers are typically specialists in a particular programming language, but are capable of contributing to projects in other languages as well. For this role, we're looking for someone who will enjoy designing, writing, and supporting open source libraries for the Python ecosystem developers that use MongoDB. This is an opportunity to make a major impact at MongoDB as Python is one of the most popular runtimes for MongoDB users, and our driver has over 3 million daily pypi downloads. You might be right for this role if you... Have substantial experience writing high-quality software in Python Have extensive knowledge in Python tools and frameworks, scientific python and web development frameworks Have practical experience with AI/ML frameworks and technologies in Python, including large language models and agentic tools are a plus Have an interest in learning and staying up-to-date with Python ecosystem trends and best practices and incorporating them into your work Can make pragmatic design decisions, balancing tradeoffs such as usability, maintainability and delivery time Want to, or already do, participate in open source software development and communities, both online via e.g. GitHub and optionally through conferences and speaking engagements Communicate well, internally and externally, both verbally and in writing Enjoy collaborating with teammates, and mentoring junior engineers and interns Are self-motivated, organized, and have strong time management skills You'll be on the team responsible for... Developing and supporting the MongoDB Python drivers and subsidiary libraries ( PyMongo , Django MongoDB Backend , PyMongoArrow , LangChain MongoDB ) and related software, collaborating with peers in our distributed world-wide engineering team Writing and maintaining open source specifications defining common behavior and APIs shared across all of our drivers Investigating bugs and support requests from commercial customers, open source users, and internal users for the libraries our team maintains Working with our Product and Server teams on designs and specifications for new user-facing MongoDB features Success in this role means... Within one month, you will understand the high-level architecture of the drivers and how MongoDB works, and will have completed a few small bug fixes and/or feature tickets Within three months, you will be contributing effectively day-to-day, fixing bugs, implementing features, investigating and responding to open source user and customer issues, and reviewing your peers' code Within six months, you'll have implemented major, planned new features, contributed to our common driver specifications, shipped a major feature in an open source library, and will be collaborating with the Product team to help craft our roadmap Within twelve months, you'll have significantly improved the quality, performance and maintainability of our codebase, and will be taking the lead in designing and specifying major new features About MongoDB MongoDB is built for change, empowering our customers and our people to innovate at the speed of the market. We have redefined the data platform for the AI era, enabling builders to create, transform, and disrupt industries with software. MongoDB’s unified data platform, the most widely available, globally distributed data platform on the market, helps organizations modernize legacy workloads, embrace innovation, and unleash AI. Our cloud-native platform, MongoDB Atlas, is the only globally distributed, multi-cloud data platform and is available across AWS, Google Cloud, and Microsoft Azure. With offices worldwide and over 67,000 customers, including 75% of the Fortune 100 and AI-native startups, relying on MongoDB for their most important applications, we’re powering the next era of software. Our compass at MongoDB is our Leadership Commitment, guiding how and why we make decisions, show up for each other, and win. It’s what makes us MongoDB. To drive the personal growth and business impact of our employees, we’re committed to developing a supportive and enriching culture for everyone. From employee affinity groups, to fertility assistance and a generous parental leave policy , we value our employees’ wellbeing and want to support them along every step of their professional and personal journeys. Learn more about what it’s like to work at MongoDB , and help us make an impact on the world! MongoDB is committed to providing any necessary accommodations for individuals with disabilities within our application and interview process. To request an accommodation due to a disability, please inform your recruiter. MongoDB, Inc. provides equal employment opportunities to all employees and applicants for employment and prohibits discrimination and harassment of any type and makes all hiring decisions without regard to race, color, religion, age, sex, national origin, disability status, genetics, protected veteran status, sexual orientation, gender identity or expression, or any other characteristic protected by federal, state or local laws. Req ID: 1273396098 MongoDB’s base salary range for this role is posted below. Compensation at the time of offer is unique to each candidate and based on a variety of factors such as skill set, experience, qualifications, and work location. Salary is one part of MongoDB’s total compensation and benefits package. Other benefits for eligible employees may include: equity, participation in the employee stock purchase program, flexible paid time off, 20 weeks fully-paid gender-neutral parental leave, fertility and adoption assistance, 401(k) plan, mental health counseling, access to transgender-inclusive health insurance coverage, and health benefits offerings. Please note, the base salary range listed below and the benefits in this paragraph are only applicable to U.S.-based candidates. MongoDB’s base salary range for this role in the U.S. is: $126,000 — $248,000 USD | M57: 0 | N57: =I57+J57 -> 0 | O57: {=OR(B57=Hist!$A$1:$A$85)} -> FALSE
A58: {=SUM((B58=$B$2:$B$127)*1)} -> 1 | B58: greenhouse|coinbase|7942306 | C58: greenhouse | D58: Coinbase | E58: coinbase | F58: 7942306 | G58: AMLCO & Senior Compliance Associate | H58: Remote - Cyprus | I58: 1 | J58: 0 | K58: https://www.coinbase.com/careers/positions/7942306?gh_jid=7942306 | L58: Ready to do the most impactful work of your career? At Coinbase , we are uncompromising on our mission to increase economic freedom. The bar is high, the environment is intense, and we like it that way. This isn't a place for complacency, it’s a place to be pushed past your perceived limits. If you're ready to build the future of finance alongside people who refuse to settle for "good enough," you belong here. Coinbase is a remote-first, but not remote-only company. Expect to get together quarterly for intense in-person working sessions called “surges.” learn more about working at Coinbase . As the AMLCO & Senior Compliance Associate for Coinbase's Cyprus MiFID entity, you'll own Financial Crime Compliance (AML/CFT) while supporting the Head of Compliance in building and running the broader compliance program. The Compliance team ensures our Cyprus operations meet CySEC and EU regulatory expectations across AML/CFT, MiFID conduct, Market Abuse, and data protection, enabling the business to scale safely. You'll combine formal AMLCO responsibilities with hands-on second-line oversight of risk assessment, monitoring, policy governance, training, and regulatory engagement. Hybrid Role: Please expect to be remote 4 days per week and in-office on Wednesdays. What you'll do: Own all AMLCO deliverables for the Cyprus MiFID entity, including the Annual AMLCO Report, AML Risk Assessment, and periodic financial crime compliance reporting to senior management and the Board. Lead second-line monitoring and testing across AML/CFT and broader conduct/compliance areas, documenting results, findings, and remediation actions for internal governance bodies. Drive regulatory engagement with CySEC, the FIU, and competent authorities, coordinating responses to information requests, inspections, and thematic reviews. Partner with first-line teams to assess the effectiveness of onboarding, KYC/EDD, sanctions screening, transaction monitoring, and STR/SAR reporting controls, escalating gaps and driving remediation. Build and maintain local compliance and AML/CFT policies, procedures, and frameworks aligned with EU/Cyprus requirements (MiFID II, AMLD, MiCA) and group-level standards. Support the Head of Compliance with day-to-day oversight, governance preparation, and key projects, serving as deputy during periods of absence. Required Skills and Experience: 4-6 years in compliance roles within Cyprus-regulated financial services, with direct AML/CFT and MiFID investment services exposure, including at least 2 years in senior-level positions. CySEC Advanced and CySEC AML certifications held. Demonstrated experience preparing AMLCO deliverables (Annual Reports, AML Risk Assessments) and executing second-line monitoring/testing programs. Proven track record engaging with CySEC, the FIU, or external auditors through inspections, thematic reviews, or regulatory reporting cycles. Hands-on experience drafting compliance policies and operating or overseeing AML/CFT frameworks within EU-regulated entities. Fluency in English required; Greek language proficiency is a strong plus. Utilizes generative AI responsibly, maintaining human oversight to deliver business-ready outputs and drive measurable improvements in workflow efficiency, cost, and quality. Req ID: P76940 #LI-Remote Pay Transparency Notice: The target annual base salary for this position can range as detailed below. Total compensation may also include equity and bonus eligibility and benefits (including medical, dental, and vision). Annual base salary range (excluding equity and bonus): €64.100 — €64.100 EUR Application Limit: Candidates may submit a maximum of 3 applications within a 6-month period. Equal Opportunity Employer: Coinbase is an Equal Opportunity Employer. All qualified applicants will receive consideration for employment without regard to race, color, religion, sex, sexual orientation, gender identity, national origin, disability, protected veteran status, or genetic information. Applicants with criminal histories will be considered consistent with applicable federal, state, and local laws. US Applicants: View Employee Rights , Know Your Rights , and E-Verify Notice of Participation. Accommodations: If you are an individual with a disability who needs a reasonable accommodation, email us your request and contact info at accommodations[at]coinbase.com. Need screen reading technology? Click here to download a free compatible screen reader and view the tutorial . Data Privacy & Arbitration: By submitting your application, you agree to our Candidate Privacy Notice . US applicants: By submitting your application, you agree to Arbitration of Disputes . AI Disclosure: Coinbase is piloting an AI tool based on machine learning technologies to conduct initial screening interviews to qualified applicants. The tool simulates realistic interview scenarios and engages in dynamic conversation. Coinbase is also piloting an AI interview intelligence platform to transcribe and summarize interview notes, allowing our interviewers to fully focus on you as the candidate. Coinbase will not use AI to make decisions impacting employment. | M58: 0 | N58: =I58+J58 -> 1 | O58: {=OR(B58=Hist!$A$1:$A$85)} -> TRUE
A59: {=SUM((B59=$B$2:$B$127)*1)} -> 1 | B59: greenhouse|coinbase|8020892 | C59: greenhouse | D59: Coinbase | E59: coinbase | F59: 8020892 | G59: Analytics Engineer | H59: Remote - USA | I59: 1 | J59: 0 | K59: https://www.coinbase.com/careers/positions/8020892?gh_jid=8020892 | L59: Ready to do the most impactful work of your career? At Coinbase , we are uncompromising on our mission to increase economic freedom. The bar is high, the environment is intense, and we like it that way. This isn't a place for complacency, it’s a place to be pushed past your perceived limits. If you're ready to build the future of finance alongside people who refuse to settle for "good enough," you belong here. Coinbase is a remote-first, but not remote-only company. Expect to get together quarterly for intense in-person working sessions called “surges.” learn more about working at Coinbase . Analytics Engineer - Compliance Data As an Analytics Engineer on the Compliance Data team within Platform , you'll build and maintain the production-grade data foundations that every regulatory obligation at Coinbase depends on. This team owns the Compliance Data Mart (CDM), Coinbase's canonical source of truth for user, transaction, and compliance data. You'll own the full lifecycle of data models and pipelines that downstream reporting, analytics, and AI workflows all build on, while also delivering accurate, timely data when regulators come calling. What you'll do: Own end-to-end development of production-grade data models and pipelines at the core of the CDM, covering user, transaction, and compliance data across retail and institutional product lines, from architecture through deployment and maintenance. Build data quality checks, data contracts, validation logic, and monitoring that protect data integrity before issues propagate to downstream reports or workflows. Partner with upstream engineering teams to fix data gaps and absorb product changes at the source, taking accountability for data issues anywhere in the stack rather than passing them downstream. Support live regulatory exams, audits, and ad hoc regulator requests with accurate, timely data, balancing time-sensitive reactive work with long-term foundational projects. Automate recurring manual workflows into scalable pipelines and self-serve tooling, enabling downstream teams and AI agents to answer their own questions. Required Skills and Experience: 2+ years of experience building and maintaining production data pipelines and data models, with strong proficiency in SQL, Python, dbt, and a modern warehouse platform (Snowflake, Databricks, or similar). Track record implementing data quality frameworks including data contracts, validation logic, reconciliation, and monitoring to catch issues before they reach downstream reports. Experience supporting time-sensitive, high-stakes data needs (regulatory exams, audits, or financial reporting) where accuracy and timeliness are non-negotiable. Demonstrated ability to turn tribal knowledge and recurring manual workflows into durable, documented infrastructure. Utilizes generative AI responsibly, maintaining human oversight to deliver business-ready outputs and drive measurable improvements in workflow efficiency, cost, and quality. Job ID: P77413 Pay Transparency Notice: Base salary varies by location (see range below). Total compensation may also include equity and bonus eligibility, and benefits (medical, dental, vision, 401(k)). Annual base salary range (excluding equity and bonus): $152,405 — $179,300 USD Application Limit: Candidates may submit a maximum of 3 applications within a 6-month period. Equal Opportunity Employer: Coinbase is an Equal Opportunity Employer. All qualified applicants will receive consideration for employment without regard to race, color, religion, sex, sexual orientation, gender identity, national origin, disability, protected veteran status, or genetic information. Applicants with criminal histories will be considered consistent with applicable federal, state, and local laws. US Applicants: View Employee Rights , Know Your Rights , and E-Verify Notice of Participation. Accommodations: If you are an individual with a disability who needs a reasonable accommodation, email us your request and contact info at accommodations[at]coinbase.com. Need screen reading technology? Click here to download a free compatible screen reader and view the tutorial . Data Privacy & Arbitration: By submitting your application, you agree to our Candidate Privacy Notice . US applicants: By submitting your application, you agree to Arbitration of Disputes . AI Disclosure: Coinbase is piloting an AI tool based on machine learning technologies to conduct initial screening interviews to qualified applicants. The tool simulates realistic interview scenarios and engages in dynamic conversation. Coinbase is also piloting an AI interview intelligence platform to transcribe and summarize interview notes, allowing our interviewers to fully focus on you as the candidate. Coinbase will not use AI to make decisions impacting employment. | M59: 0 | N59: =I59+J59 -> 1 | O59: {=OR(B59=Hist!$A$1:$A$85)} -> TRUE
A60: {=SUM((B60=$B$2:$B$127)*1)} -> 1 | B60: greenhouse|coinbase|8024880 | C60: greenhouse | D60: Coinbase | E60: coinbase | F60: 8024880 | G60: Analytics Engineer, GFCO Analytics | H60: Remote - USA | I60: 1 | J60: 0 | K60: https://www.coinbase.com/careers/positions/8024880?gh_jid=8024880 | L60: Ready to do the most impactful work of your career? At Coinbase , we are uncompromising on our mission to increase economic freedom. The bar is high, the environment is intense, and we like it that way. This isn't a place for complacency, it’s a place to be pushed past your perceived limits. If you're ready to build the future of finance alongside people who refuse to settle for "good enough," you belong here. Coinbase is a remote-first, but not remote-only company. Expect to get together quarterly for intense in-person working sessions called “surges.” learn more about working at Coinbase . We're hiring an Analytics Engineer to join the GFCO Analytics Engineering team and build the data foundations that power customer experience and compliance operations at Coinbase. You'll own end-to-end data pipelines, develop trusted metrics, and enable CX stakeholders to make faster, better decisions with clean, reliable data. This is a high-impact role where you'll directly influence how we serve and protect our customers while scaling our analytics capabilities. What you'll do: Own the design, build, and maintenance of data models and pipelines that support CX operations, compliance reporting, and customer insights, ensuring data is accurate, timely, and well-documented. Partner with CX Operations, Compliance, and Product teams to translate business needs into data requirements and deliver self-serve analytics solutions that reduce manual effort. Build and maintain dashboards, metrics, and reporting tools that give CX leaders visibility into performance, customer trends, and compliance health. Drive data quality and governance within the CX data domain by implementing testing, monitoring, and documentation standards that ensure stakeholder trust in the data. Identify opportunities to automate recurring data workflows and reporting processes, shifting the team from reactive requests toward scalable, self-serve solutions. Collaborate with broader Data Engineering and Analytics teams to align on best practices, share learnings, and contribute to Coinbase's overall data infrastructure. Required Skills and Experience: 3+ years of experience in analytics engineering, data engineering, or a related data role, with hands-on experience building and maintaining data pipelines and models. Proficiency in SQL and experience with modern data stack tools such as dbt, Airflow, and cloud data warehouses (Snowflake, Databricks, or similar). Experience with data modeling concepts (dimensional modeling, star/snowflake schemas) and building trusted, well-documented data products. Familiarity with BI/visualization tools (Looker, Tableau, or similar) and experience building dashboards and self-serve analytics solutions. Track record of partnering with non-technical stakeholders to translate business needs into data solutions, particularly in customer experience, operations, or compliance domains. Utilizes generative AI responsibly, maintaining human oversight to deliver business-ready outputs and drive measurable improvements in workflow efficiency, cost, and quality. Pay Transparency Notice: Base salary varies by location (see range below). Total compensation may also include equity and bonus eligibility, and benefits (medical, dental, vision, 401(k)). Annual base salary range (excluding equity and bonus): $152,405 — $179,300 USD Application Limit: Candidates may submit a maximum of 3 applications within a 6-month period. Equal Opportunity Employer: Coinbase is an Equal Opportunity Employer. All qualified applicants will receive consideration for employment without regard to race, color, religion, sex, sexual orientation, gender identity, national origin, disability, protected veteran status, or genetic information. Applicants with criminal histories will be considered consistent with applicable federal, state, and local laws. US Applicants: View Employee Rights , Know Your Rights , and E-Verify Notice of Participation. Accommodations: If you are an individual with a disability who needs a reasonable accommodation, email us your request and contact info at accommodations[at]coinbase.com. Need screen reading technology? Click here to download a free compatible screen reader and view the tutorial . Data Privacy & Arbitration: By submitting your application, you agree to our Candidate Privacy Notice . US applicants: By submitting your application, you agree to Arbitration of Disputes . AI Disclosure: Coinbase is piloting an AI tool based on machine learning technologies to conduct initial screening interviews to qualified applicants. The tool simulates realistic interview scenarios and engages in dynamic conversation. Coinbase is also piloting an AI interview intelligence platform to transcribe and summarize interview notes, allowing our interviewers to fully focus on you as the candidate. Coinbase will not use AI to make decisions impacting employment. | M60: 0 | N60: =I60+J60 -> 1 | O60: {=OR(B60=Hist!$A$1:$A$85)} -> TRUE
A61: {=SUM((B61=$B$2:$B$127)*1)} -> 1 | B61: greenhouse|coinbase|8031260 | C61: greenhouse | D61: Coinbase | E61: coinbase | F61: 8031260 | G61: Machine Learning Engineer, CX Intelligence | H61: Remote - Brazil | I61: 1 | J61: 0 | K61: https://www.coinbase.com/careers/positions/8031260?gh_jid=8031260 | L61: Ready to do the most impactful work of your career? At Coinbase , we are uncompromising on our mission to increase economic freedom. The bar is high, the environment is intense, and we like it that way. This isn't a place for complacency, it’s a place to be pushed past your perceived limits. If you're ready to build the future of finance alongside people who refuse to settle for "good enough," you belong here. Coinbase is a remote-first, but not remote-only company. Expect to get together quarterly for intense in-person working sessions called “surges.” learn more about working at Coinbase . The CX Intelligence Engineering team, part of Coinbase's Enterprise Applications and Architecture org, builds the multi-agent platform powering Coinbase Chat, Help Center, and agent tooling. As a Machine Learning Engineer on this team, you'll design and scale the agentic systems that automate complex customer support workflows, connecting LLMs with internal APIs and tools to deliver fast, accurate, and compliant AI-powered experiences for millions of customers. What you'll do: Architect multi-agent systems using advanced orchestration frameworks (LangGraph, Google ADK) to automate complex customer support procedures end-to-end. Build and scale integrations using Model Context Protocol (MCP) to connect LLMs with internal Coinbase APIs, databases, and third-party tooling. Develop automated "LLM-as-a-judge" evaluation pipelines to monitor, measure, and improve the performance of non-deterministic AI agents in production. Implement RAG, fine-tuning, and prompt engineering techniques to ensure chatbot responses are grounded, accurate, and compliant with Coinbase policies. Ship production-ready Python services that are resilient, low-latency, and capable of handling Coinbase-scale traffic across asynchronous microservices. Partner with Conversation Design and Product to translate complex business logic into executable agent procedures within the decentralized architecture. Required Skills and Experience: 3+ years building and scaling ML/AI systems in production, with demonstrated experience implementing agentic "Loop" or "ReAct" based systems where AI takes actions autonomously. Deep understanding of the LLM lifecycle including context window management, token optimization, structured output parsing (Pydantic, JSON mode), and multi-agent orchestration frameworks (LangGraph, Google ADK, or similar). Strong proficiency in Python with hands-on experience in microservices architecture, asynchronous programming, high-throughput APIs, and vector databases (Pinecone, Weaviate, or equivalent). Demonstrated ability to explain model behaviors and technical trade-offs to non-technical stakeholders across CX, Legal, and Product teams. Utilizes generative AI responsibly, maintaining human oversight to deliver business-ready outputs and drive measurable improvements in workflow efficiency, cost, and quality. Job ID: P77545 Pay Transparency Notice: The target annual base salary for this position can range as detailed below. Total compensation may also include equity and bonus eligibility and benefits (including medical, dental, and vision). Annual base salary range (excluding equity and bonus): R$347.900 — R$347.900 BRL Application Limit: Candidates may submit a maximum of 3 applications within a 6-month period. Equal Opportunity Employer: Coinbase is an Equal Opportunity Employer. All qualified applicants will receive consideration for employment without regard to race, color, religion, sex, sexual orientation, gender identity, national origin, disability, protected veteran status, or genetic information. Applicants with criminal histories will be considered consistent with applicable federal, state, and local laws. US Applicants: View Employee Rights , Know Your Rights , and E-Verify Notice of Participation. Accommodations: If you are an individual with a disability who needs a reasonable accommodation, email us your request and contact info at accommodations[at]coinbase.com. Need screen reading technology? Click here to download a free compatible screen reader and view the tutorial . Data Privacy & Arbitration: By submitting your application, you agree to our Candidate Privacy Notice . US applicants: By submitting your application, you agree to Arbitration of Disputes . AI Disclosure: Coinbase is piloting an AI tool based on machine learning technologies to conduct initial screening interviews to qualified applicants. The tool simulates realistic interview scenarios and engages in dynamic conversation. Coinbase is also piloting an AI interview intelligence platform to transcribe and summarize interview notes, allowing our interviewers to fully focus on you as the candidate. Coinbase will not use AI to make decisions impacting employment. | M61: 0 | N61: =I61+J61 -> 1 | O61: {=OR(B61=Hist!$A$1:$A$85)} -> TRUE
A62: {=SUM((B62=$B$2:$B$127)*1)} -> 1 | B62: greenhouse|coinbase|7984814 | C62: greenhouse | D62: Coinbase | E62: coinbase | F62: 7984814 | G62: Payments Risk Analyst II | H62: Remote - USA | I62: 1 | J62: 0 | K62: https://www.coinbase.com/careers/positions/7984814?gh_jid=7984814 | L62: Ready to do the most impactful work of your career? At Coinbase , we are uncompromising on our mission to increase economic freedom. The bar is high, the environment is intense, and we like it that way. This isn't a place for complacency, it’s a place to be pushed past your perceived limits. If you're ready to build the future of finance alongside people who refuse to settle for "good enough," you belong here. Coinbase is a remote-first, but not remote-only company. Expect to get together quarterly for intense in-person working sessions called “surges.” learn more about working at Coinbase . Payments Risk Analyst II As a Payments Risk Analyst II on the Risk & Fraud team within the Consumer & Business group, you'll own the identification and mitigation of fraud risk across Coinbase's fiat payment rails, protecting the company's bottom line and millions of customers without degrading the user experience. You'll join a team that is modernizing its risk controls and building next-generation fraud prevention systems, giving you the opportunity to shape how we protect customers at scale across one of crypto's highest-volume retail platforms. What you'll do: Own end-to-end risk controls for ACH payments, scaling fraud prevention processes to keep pace with business expansion. Drive detection and mitigation of fraudulent deposit activity by implementing targeting logic against bad actors and high-risk behavior. Lead quantitative analysis of fraud performance, measuring rule precision and recall, assessing the financial impact of decisions, and surfacing tradeoffs to leadership with clear, data-backed recommendations. Partner cross-functionally with Product, Growth, Data Science, Risk ML, and Engineering to develop and iterate on risk management strategies, including the transition from heuristic rules to model-driven and synchronous friction controls. Execute investigations into anomalous customer and transaction behavior, proactively identifying monitoring gaps and closing them before they become losses. Required Skills and Experience: 4+ years of experience in risk, fraud, or payments operations, with at least 2 years focused on payments fraud prevention in a fintech, e-commerce, or financial services environment. 2+ years of hands-on experience querying and analyzing large datasets using SQL, with the ability to independently scope and execute analytics projects end-to-end. Demonstrated experience using identity-provider data and fraud-detection tooling to implement and tune risk controls. Proven ability to measure the financial impact of fraud decisions and communicate findings to senior leadership and cross-functional stakeholders. Demonstrated working knowledge of ACH payment processing and applicable NACHA rules. Utilizes generative AI responsibly, maintaining human oversight to deliver business-ready outputs and drive measurable improvements in workflow efficiency, cost, and quality. Pay Transparency Notice: Base salary varies by location (see range below). Total compensation may also include equity and bonus eligibility, and benefits (medical, dental, vision, 401(k)). Annual base salary range (excluding equity and bonus): $135,320 — $159,200 USD Application Limit: Candidates may submit a maximum of 3 applications within a 6-month period. Equal Opportunity Employer: Coinbase is an Equal Opportunity Employer. All qualified applicants will receive consideration for employment without regard to race, color, religion, sex, sexual orientation, gender identity, national origin, disability, protected veteran status, or genetic information. Applicants with criminal histories will be considered consistent with applicable federal, state, and local laws. US Applicants: View Employee Rights , Know Your Rights , and E-Verify Notice of Participation. Accommodations: If you are an individual with a disability who needs a reasonable accommodation, email us your request and contact info at accommodations[at]coinbase.com. Need screen reading technology? Click here to download a free compatible screen reader and view the tutorial . Data Privacy & Arbitration: By submitting your application, you agree to our Candidate Privacy Notice . US applicants: By submitting your application, you agree to Arbitration of Disputes . AI Disclosure: Coinbase is piloting an AI tool based on machine learning technologies to conduct initial screening interviews to qualified applicants. The tool simulates realistic interview scenarios and engages in dynamic conversation. Coinbase is also piloting an AI interview intelligence platform to transcribe and summarize interview notes, allowing our interviewers to fully focus on you as the candidate. Coinbase will not use AI to make decisions impacting employment. | M62: 0 | N62: =I62+J62 -> 1 | O62: {=OR(B62=Hist!$A$1:$A$85)} -> TRUE
A63: {=SUM((B63=$B$2:$B$127)*1)} -> 1 | B63: greenhouse|coinbase|7736521 | C63: greenhouse | D63: Coinbase | E63: coinbase | F63: 7736521 | G63: Senior Analytics Engineer (Platform - Financial Analytics) | H63: Remote - USA | I63: 1 | J63: 0 | K63: https://www.coinbase.com/careers/positions/7736521?gh_jid=7736521 | L63: Ready to do the most impactful work of your career? At Coinbase , we are uncompromising on our mission to increase economic freedom. The bar is high, the environment is intense, and we like it that way. This isn't a place for complacency, it’s a place to be pushed past your perceived limits. If you're ready to build the future of finance alongside people who refuse to settle for "good enough," you belong here. Coinbase is a remote-first, but not remote-only company. Expect to get together quarterly for intense in-person working sessions called “surges.” learn more about working at Coinbase . Senior Analytics Engineer As a Senior Analytics Engineer on the Platform team, you'll build the scalable data models and pipelines that power analytics, experimentation, and decision-making across Coinbase. Our Analytics Engineering team transforms raw data into trusted, well-modeled sources that stakeholders across Product, Engineering, and Data Science rely on daily. You'll own end-to-end data solutions for specific business domains, turning complex data flows into clean, reusable frameworks that unlock commercial value at scale. What you'll do: Own end-to-end data modeling for assigned business domains, from understanding source system data flows through designing modular, reusable models (star/snowflake schemas) that serve as the single source of truth for downstream teams. Build and optimize ETL/ELT pipelines using modern tools like dbt and Airflow, ensuring data quality, reliability, and performance at scale across Snowflake or similar warehouse architectures. Partner with Engineering, Product, and Data Science teams to identify data gaps, define requirements, and deliver data products that directly enable experimentation, ad hoc analysis, and business metric optimization. Develop scalable abstractions and frameworks (UDFs, Python packages, internal data apps) that multiply the efficiency of other data teams and reduce time-to-insight across the organization. Design and deliver dashboards and visualization layers using tools like Looker or Tableau, translating complex data into clear, actionable views for cross-functional stakeholders. Required Skills and Experience: 5+ years in analytics engineering or data engineering with demonstrated expertise in designing modular data models and building production ETL/ELT pipelines using dbt, Airflow, or similar. Advanced SQL proficiency for complex transformations and query optimization, plus intermediate-to-advanced Python for scripting, automation, and building scalable frameworks (OOP experience preferred). Production experience with modern data warehouse architectures (Snowflake, Databricks) including performance tuning, data quality monitoring, and version-controlled development workflows (GitHub, CI/CD). Proven track record delivering data solutions that generated measurable business impact, with the ability to independently build domain expertise and communicate technical trade-offs to Product, Engineering, and business stakeholders. Experience with prompt engineering for LLMs (e.g., GPT), including designing and optimizing prompts for internal tooling and automation use cases. Utilizes generative AI responsibly, maintaining human oversight to deliver business-ready outputs and drive measurable improvements in workflow efficiency, cost, and quality. Pay Transparency Notice: Base salary varies by location (see range below). Total compensation may also include equity and bonus eligibility, and benefits (medical, dental, vision, 401(k)). Annual base salary range (excluding equity and bonus): $180,370 — $212,200 USD Application Limit: Candidates may submit a maximum of 3 applications within a 6-month period. Equal Opportunity Employer: Coinbase is an Equal Opportunity Employer. All qualified applicants will receive consideration for employment without regard to race, color, religion, sex, sexual orientation, gender identity, national origin, disability, protected veteran status, or genetic information. Applicants with criminal histories will be considered consistent with applicable federal, state, and local laws. US Applicants: View Employee Rights , Know Your Rights , and E-Verify Notice of Participation. Accommodations: If you are an individual with a disability who needs a reasonable accommodation, email us your request and contact info at accommodations[at]coinbase.com. Need screen reading technology? Click here to download a free compatible screen reader and view the tutorial . Data Privacy & Arbitration: By submitting your application, you agree to our Candidate Privacy Notice . US applicants: By submitting your application, you agree to Arbitration of Disputes . AI Disclosure: Coinbase is piloting an AI tool based on machine learning technologies to conduct initial screening interviews to qualified applicants. The tool simulates realistic interview scenarios and engages in dynamic conversation. Coinbase is also piloting an AI interview intelligence platform to transcribe and summarize interview notes, allowing our interviewers to fully focus on you as the candidate. Coinbase will not use AI to make decisions impacting employment. | M63: 0 | N63: =I63+J63 -> 1 | O63: {=OR(B63=Hist!$A$1:$A$85)} -> TRUE
A64: {=SUM((B64=$B$2:$B$127)*1)} -> 1 | B64: greenhouse|coinbase|8009392 | C64: greenhouse | D64: Coinbase | E64: coinbase | F64: 8009392 | G64: Senior Data Scientist, CX Analytics | H64: Remote - USA | I64: 1 | J64: 0 | K64: https://www.coinbase.com/careers/positions/8009392?gh_jid=8009392 | L64: Ready to do the most impactful work of your career? At Coinbase , we are uncompromising on our mission to increase economic freedom. The bar is high, the environment is intense, and we like it that way. This isn't a place for complacency, it’s a place to be pushed past your perceived limits. If you're ready to build the future of finance alongside people who refuse to settle for "good enough," you belong here. Coinbase is a remote-first, but not remote-only company. Expect to get together quarterly for intense in-person working sessions called “surges.” learn more about working at Coinbase . As a Senior Data Scientist on the CX Consumer Analytics team, you will serve as the foundational link between CX operations and top-line financial impact, owning the revenue calibration models, experimentation frameworks, and behavioral intelligence that connect every customer support interaction to Coinbase's asset accumulation flywheel. You will partner closely with CX Analytics Engineers, Program Managers, and Product teams to translate complex operational and behavioral data into defensible, executive-ready insights that drive measurable improvements in retention, product adoption, and automation quality. What you'll do: Own and evolve CX's Downstream Impact of Support (DSI) revenue calibration models, translating support interaction data into quantified revenue signals. Design and execute causal inference frameworks and experiments to measure the incremental impact of CX programs (Concierge, Proactive Outreach, automation interventions) on customer retention and product engagement. Build and maintain LLM-powered classification pipelines for CX contact taxonomy, customer friction detection, and issue attribution, partnering with Analytics Engineers to productionize models into CX's governed Source of Truth infrastructure. Partner with CX Program Managers and Product teams to define segmentation models and behavioral signals that enable personalized experiences and improve business outcomes. Maintain a high bar for statistical rigor across CX's analytics function, ensuring experimentation, causal analyses, and model outputs meet the standards required for executive reporting and regulatory defensibility. Required Skills and Experience: A BA/BS in a quantitative field (e.g., Statistics, Mathematics, Computer Science, Economics) with 5+ years of relevant experience, or a PhD in a quantitative field with 3+ years of relevant experience. Demonstrated experience building revenue attribution or causal impact models and driving data science projects through ambiguous problem spaces in a consumer-facing or operational analytics context. Practical expertise applying statistical concepts including A/B testing, causal inference, and ML to real-world business problems, with a high bar for production-grade accuracy and evaluation rigor. Experience designing and deploying LLM-based classification or NLP pipelines for operational or customer-facing use cases. Ability to influence cross-functional stakeholders by synthesizing complex model outputs into clear, actionable narratives for executive and product audiences. Demonstrates the ability to responsibly use generative AI tools and copilots (e.g., LibreChat, Gemini, Glean) in daily workflows, continuously learn as tools evolve, and apply human‑in‑the‑loop practices to deliver business‑ready outputs and drive measurable improvements in efficiency, cost, and quality. Pay Transparency Notice: Base salary varies by location (see range below). Total compensation may also include equity and bonus eligibility, and benefits (medical, dental, vision, 401(k)). Annual base salary range (excluding equity and bonus): $180,370 — $212,000 USD Application Limit: Candidates may submit a maximum of 3 applications within a 6-month period. Equal Opportunity Employer: Coinbase is an Equal Opportunity Employer. All qualified applicants will receive consideration for employment without regard to race, color, religion, sex, sexual orientation, gender identity, national origin, disability, protected veteran status, or genetic information. Applicants with criminal histories will be considered consistent with applicable federal, state, and local laws. US Applicants: View Employee Rights , Know Your Rights , and E-Verify Notice of Participation. Accommodations: If you are an individual with a disability who needs a reasonable accommodation, email us your request and contact info at accommodations[at]coinbase.com. Need screen reading technology? Click here to download a free compatible screen reader and view the tutorial . Data Privacy & Arbitration: By submitting your application, you agree to our Candidate Privacy Notice . US applicants: By submitting your application, you agree to Arbitration of Disputes . AI Disclosure: Coinbase is piloting an AI tool based on machine learning technologies to conduct initial screening interviews to qualified applicants. The tool simulates realistic interview scenarios and engages in dynamic conversation. Coinbase is also piloting an AI interview intelligence platform to transcribe and summarize interview notes, allowing our interviewers to fully focus on you as the candidate. Coinbase will not use AI to make decisions impacting employment. | M64: 0 | N64: =I64+J64 -> 1 | O64: {=OR(B64=Hist!$A$1:$A$85)} -> TRUE
A65: {=SUM((B65=$B$2:$B$127)*1)} -> 1 | B65: greenhouse|coinbase|7739592 | C65: greenhouse | D65: Coinbase | E65: coinbase | F65: 7739592 | G65: Senior Machine Learning Engineer | H65: Remote - India | I65: 1 | J65: 0 | K65: https://www.coinbase.com/careers/positions/7739592?gh_jid=7739592 | L65: Ready to do the most impactful work of your career? At Coinbase , we are uncompromising on our mission to increase economic freedom. The bar is high, the environment is intense, and we like it that way. This isn't a place for complacency, it’s a place to be pushed past your perceived limits. If you're ready to build the future of finance alongside people who refuse to settle for "good enough," you belong here. Coinbase is a remote-first, but not remote-only company. Expect to get together quarterly for intense in-person working sessions called “surges.” learn more about working at Coinbase . The CX Intelligence team is part of Coinbase’s Enterprise Applications and Architecture org and builds the customer-facing and internal CX experiences that connect the Help Center, chatbots (CBCB), and agent workflows. The team owns the multi-agent platform which powers coinbase chat, Help Center and agent tooling surfaces, partnering closely with Conversation Design, CX, and other Engg teams to deliver secure, compliant, and scalable AI-powered support. Our work provides the trusted and accurate automated and agent-assisted experiences—helping customers get answers faster while enabling human agents to resolve cases more effectively. We are hiring an IC5 Machine Learning Engineer to drive the evolution of our conversational ecosystem by building a seamless hybrid vendor-internal chatbot experience. You will lead the design and implementation of a sophisticated unified orchestration layer that coordinates interactions between vendor AI, internal multi-agent systems, and human participants. This role is pivotal in managing complex state transitions, context sharing, and intent routing across a distributed environment. You’ll thrive here if you enjoy high ownership, architecting complex hand-off logic between disparate LLM frameworks, and building reliable AI-enabled products that are fast, measurable, and scalable. What you'll do: Architect and deploy the orchestration layer that manages state transitions, context sharing, and intent routing across vendor and internal LLM frameworks in a distributed conversational environment. Build production-grade Python services that bridge advanced ML/AI research with reliable, measurable customer-facing products. Lead end-to-end project execution for complex ML initiatives, managing priorities, technical trade-offs, and cross-functional dependencies from design through delivery. Establish best practices for system design, coding standards, and AI/ML development workflows across the team. Mentor engineers on architectural integrity and modern AI/ML patterns, raising the technical bar for the broader team. Conduct design reviews to ensure every feature meets Coinbase's standards for security, scalability, and performance. Required Skills and Experience: 5+ years of professional experience in machine learning and software engineering, with a track record of shipping production-grade ML services at scale. Hands-on expertise building with modern AI architectures (LLMs, deep learning) and the generative AI ecosystem, including frameworks such as LangGraph, LangSmith, Google ADK, Vertex AI, or AWS Bedrock. Deep proficiency in Python with demonstrated ability to write clean, maintainable, highly-tested production code. Specialized knowledge in at least one domain: NLP, information retrieval, computer vision, or advanced statistical modeling. Proven ability to write technical design documents and present ML system architectures to cross-functional stakeholders, translating complex technical concepts for non-technical audiences. Utilizes generative AI responsibly, maintaining human oversight to deliver business-ready outputs and drive measurable improvements in workflow efficiency, cost, and quality. Demonstrates the ability to responsibly use generative AI tools and copilots (e.g., LibreChat, Gemini, Glean) in daily workflows, continuously learn as tools evolve, and apply human‑in‑the‑loop practices to deliver business‑ready outputs and drive measurable improvements in efficiency, cost, and quality. Pay Transparency Notice: The target annual base salary for this position can range as detailed below. Total compensation may also include equity and bonus eligibility and benefits (including medical, dental, and vision). Annual base salary range (excluding equity and bonus): ₹6,612,600 — ₹6,612,600 INR Application Limit: Candidates may submit a maximum of 3 applications within a 6-month period. Equal Opportunity Employer: Coinbase is an Equal Opportunity Employer. All qualified applicants will receive consideration for employment without regard to race, color, religion, sex, sexual orientation, gender identity, national origin, disability, protected veteran status, or genetic information. Applicants with criminal histories will be considered consistent with applicable federal, state, and local laws. US Applicants: View Employee Rights , Know Your Rights , and E-Verify Notice of Participation. Accommodations: If you are an individual with a disability who needs a reasonable accommodation, email us your request and contact info at accommodations[at]coinbase.com. Need screen reading technology? Click here to download a free compatible screen reader and view the tutorial . Data Privacy & Arbitration: By submitting your application, you agree to our Candidate Privacy Notice . US applicants: By submitting your application, you agree to Arbitration of Disputes . AI Disclosure: Coinbase is piloting an AI tool based on machine learning technologies to conduct initial screening interviews to qualified applicants. The tool simulates realistic interview scenarios and engages in dynamic conversation. Coinbase is also piloting an AI interview intelligence platform to transcribe and summarize interview notes, allowing our interviewers to fully focus on you as the candidate. Coinbase will not use AI to make decisions impacting employment. | M65: 0 | N65: =I65+J65 -> 1 | O65: {=OR(B65=Hist!$A$1:$A$85)} -> TRUE
A66: {=SUM((B66=$B$2:$B$127)*1)} -> 1 | B66: greenhouse|coinbase|8008569 | C66: greenhouse | D66: Coinbase | E66: coinbase | F66: 8008569 | G66: Senior Machine Learning Engineer, CX Intelligence | H66: Remote - Brazil | I66: 1 | J66: 0 | K66: https://www.coinbase.com/careers/positions/8008569?gh_jid=8008569 | L66: Ready to do the most impactful work of your career? At Coinbase , we are uncompromising on our mission to increase economic freedom. The bar is high, the environment is intense, and we like it that way. This isn't a place for complacency, it’s a place to be pushed past your perceived limits. If you're ready to build the future of finance alongside people who refuse to settle for "good enough," you belong here. Coinbase is a remote-first, but not remote-only company. Expect to get together quarterly for intense in-person working sessions called “surges.” learn more about working at Coinbase . As a Machine Learning Engineer on the CX Intelligence team within Enterprise Applications and Architecture, you'll build the AI-powered conversational systems that connect Coinbase's Help Center, chatbots, and agent workflows. The team owns the multi-agent platform powering Coinbase Chat and agent tooling, partnering with Conversation Design, CX, and Engineering to deliver secure, scalable automated support. You'll lead the design and implementation of a unified orchestration layer that coordinates interactions between vendor AI, internal multi-agent systems, and human participants, directly improving how millions of customers get help. What you'll do: Architect and deploy the orchestration layer that manages state transitions, context sharing, and intent routing across vendor and internal LLM frameworks in a distributed conversational environment. Build production-grade Python services that bridge advanced ML/AI research with reliable, measurable customer-facing products. Lead end-to-end project execution for complex ML initiatives, managing priorities, technical trade-offs, and cross-functional dependencies from design through delivery. Establish best practices for system design, coding standards, and AI/ML development workflows across the team. Mentor engineers on architectural integrity and modern AI/ML patterns, raising the technical bar for the broader team. Conduct design reviews to ensure every feature meets Coinbase's standards for security, scalability, and performance. Required Skills and Experience: 5+ years of professional experience in machine learning and software engineering, with a track record of shipping production-grade ML services at scale. Hands-on expertise building with modern AI architectures (LLMs, deep learning) and the generative AI ecosystem, including frameworks such as LangGraph, LangSmith, Google ADK, Vertex AI, or AWS Bedrock. Deep proficiency in Python with demonstrated ability to write clean, maintainable, highly-tested production code. Specialized knowledge in at least one domain: NLP, information retrieval, computer vision, or advanced statistical modeling. Proven ability to write technical design documents and present ML system architectures to cross-functional stakeholders, translating complex technical concepts for non-technical audiences. Utilizes generative AI responsibly, maintaining human oversight to deliver business-ready outputs and drive measurable improvements in workflow efficiency, cost, and quality. Pay Transparency Notice: The target annual base salary for this position can range as detailed below. Total compensation may also include equity and bonus eligibility and benefits (including medical, dental, and vision). Annual base salary range (excluding equity and bonus): R$455.500 — R$455.500 BRL Application Limit: Candidates may submit a maximum of 3 applications within a 6-month period. Equal Opportunity Employer: Coinbase is an Equal Opportunity Employer. All qualified applicants will receive consideration for employment without regard to race, color, religion, sex, sexual orientation, gender identity, national origin, disability, protected veteran status, or genetic information. Applicants with criminal histories will be considered consistent with applicable federal, state, and local laws. US Applicants: View Employee Rights , Know Your Rights , and E-Verify Notice of Participation. Accommodations: If you are an individual with a disability who needs a reasonable accommodation, email us your request and contact info at accommodations[at]coinbase.com. Need screen reading technology? Click here to download a free compatible screen reader and view the tutorial . Data Privacy & Arbitration: By submitting your application, you agree to our Candidate Privacy Notice . US applicants: By submitting your application, you agree to Arbitration of Disputes . AI Disclosure: Coinbase is piloting an AI tool based on machine learning technologies to conduct initial screening interviews to qualified applicants. The tool simulates realistic interview scenarios and engages in dynamic conversation. Coinbase is also piloting an AI interview intelligence platform to transcribe and summarize interview notes, allowing our interviewers to fully focus on you as the candidate. Coinbase will not use AI to make decisions impacting employment. | M66: 0 | N66: =I66+J66 -> 1 | O66: {=OR(B66=Hist!$A$1:$A$85)} -> TRUE
A67: {=SUM((B67=$B$2:$B$127)*1)} -> 1 | B67: greenhouse|coinbase|8008047 | C67: greenhouse | D67: Coinbase | E67: coinbase | F67: 8008047 | G67: Senior Program Manager, Contracts & Analytics | H67: Remote - USA | I67: 1 | J67: 0 | K67: https://www.coinbase.com/careers/positions/8008047?gh_jid=8008047 | L67: Ready to do the most impactful work of your career? At Coinbase , we are uncompromising on our mission to increase economic freedom. The bar is high, the environment is intense, and we like it that way. This isn't a place for complacency, it’s a place to be pushed past your perceived limits. If you're ready to build the future of finance alongside people who refuse to settle for "good enough," you belong here. Coinbase is a remote-first, but not remote-only company. Expect to get together quarterly for intense in-person working sessions called “surges.” learn more about working at Coinbase . As a Senior Program Manager, Contracts & Analytics, you'll join Coinbase's Legal Operations team to own the strategic direction, in-house build roadmap, and ongoing optimization of our Contract Lifecycle Management (CLM) ecosystem. This role goes beyond configuration - you'll define what gets built, set the technical vision for contracting workflows, and drive AI enablement across the team. You'll serve as a strategic partner to Institutional Sales, Enterprise Architecture, and Engineering, ensuring Coinbase's contracting infrastructure scales with the business and delivers measurable speed, compliance, and insight improvements. What you'll do: Own the CLM technology roadmap and backlog, setting strategic direction for what to build, integrate, or optimize across Ironclad, Evisort, Salesforce, and emerging tools, and translating that vision into a prioritized delivery plan. Lead in-house builds and workflow development that extend beyond standard SaaS configuration, partnering with Enterprise Architecture and Engineering to design scalable, integrated contracting solutions. Drive AI enablement for the Legal Operations team by identifying high-impact automation opportunities, standing up proof of concepts (e.g., N8N, Workato, Claude, Glean), and facilitating trainings, office hours, and adoption programs that raise the team's AI fluency. Develop and manage the comprehensive contracts reporting framework and system of record for all agreements, including data extraction, metadata integrity, and data models that surface actionable insights to Institutional Sales and Legal leadership. Communicate roadmap enhancements, program outcomes, and strategic recommendations to senior stakeholders, ensuring cross-functional alignment on contracting priorities and technology investments. Lead large, cross-functional contracts initiatives end-to-end, managing dependencies across Legal, Sales, Engineering, and Compliance, and delivering on time and within scope. Required Skills and Experience: 8+ years of program or project management experience within Legal Operations, contract management, or a technology-driven operations function, with a track record of setting strategic direction for tooling and workflows, not just executing on them. Demonstrated experience owning a technology roadmap and backlog, including prioritizing build-vs-buy decisions, scoping in-house development work, and partnering with engineering and architecture teams to deliver integrated solutions. Expert-level, hands-on experience with Contract Lifecycle Management (CLM) systems (Ironclad required), including workflow design, template management, reporting, and integration planning with platforms like Salesforce. Proven ability to drive AI and automation adoption within a team, including evaluating tools, building proof of concepts, and leading enablement programs that result in measurable workflow improvements. Working knowledge of legal technology and AI-driven contract review tools (e.g., Evisort), with experience in data extraction, metadata management, and building reporting frameworks that serve as the system of record for agreements. Utilizes generative AI responsibly, maintaining human oversight to deliver business-ready outputs and drive measurable improvements in workflow efficiency, cost, and quality. Postion ID: P77368 #LI-Remote Pay Transparency Notice: Base salary varies by location (see range below). Total compensation may also include equity and bonus eligibility, and benefits (medical, dental, vision, 401(k)). Annual base salary range (excluding equity and bonus): $148,835 — $175,100 USD Application Limit: Candidates may submit a maximum of 3 applications within a 6-month period. Equal Opportunity Employer: Coinbase is an Equal Opportunity Employer. All qualified applicants will receive consideration for employment without regard to race, color, religion, sex, sexual orientation, gender identity, national origin, disability, protected veteran status, or genetic information. Applicants with criminal histories will be considered consistent with applicable federal, state, and local laws. US Applicants: View Employee Rights , Know Your Rights , and E-Verify Notice of Participation. Accommodations: If you are an individual with a disability who needs a reasonable accommodation, email us your request and contact info at accommodations[at]coinbase.com. Need screen reading technology? Click here to download a free compatible screen reader and view the tutorial . Data Privacy & Arbitration: By submitting your application, you agree to our Candidate Privacy Notice . US applicants: By submitting your application, you agree to Arbitration of Disputes . AI Disclosure: Coinbase is piloting an AI tool based on machine learning technologies to conduct initial screening interviews to qualified applicants. The tool simulates realistic interview scenarios and engages in dynamic conversation. Coinbase is also piloting an AI interview intelligence platform to transcribe and summarize interview notes, allowing our interviewers to fully focus on you as the candidate. Coinbase will not use AI to make decisions impacting employment. | M67: 0 | N67: =I67+J67 -> 1 | O67: {=OR(B67=Hist!$A$1:$A$85)} -> TRUE
... A127: {=SUM((B127=$B$2:$B$127)*1)} -> 1 | B127: ashby|supabase|44f6de1c-0fdc-4d46-aa3e-7d57b8be38b2 | C127: ashby | D127: Supabase | E127: supabase | F127: 44f6de1c-0fdc-4d46-aa3e-7d57b8be38b2 | G127: Senior Data Engineer | H127: Remote | I127: 1 | J127: 0 | K127: https://jobs.ashbyhq.com/supabase/44f6de1c-0fdc-4d46-aa3e-7d57b8be38b2 | L127: ABOUT SUPABASE Supabase is the Postgres development platform, built by developers for developers. We provide a complete backend solution including Database, Auth, Storage, Edge Functions, Realtime, and Vector Search. All services are deeply integrated and designed for growth. ABOUT THE ROLE We're looking for a Senior Data Engineer to join our Data team and own data systems end to end, from the raw source all the way to the analysis that drives decisions. You'll report to the Lead Data Engineer and work closely with growth, finance, and product, helping the whole company understand what's happening and why. This is a wide role. You'll build and operate the pipelines, model the data, manage the infrastructure, and deliver the analysis yourself. We're scaling fast, so the systems you build need to hold up when the data multiplies. If you like owning the full picture instead of a single layer, this is for you. At Supabase, data runs the company. Growth bets, billing, and product decisions all ride on the pipelines and models the Data team owns, across multi-terabyte tables and billions of events that grow every week. This role is for someone who wants to own that, not just report on it. WHAT YOU'LL BE RESPONSIBLE FOR In this role, you'll: - Own data from source to delivery. Design ingestion from source systems into BigQuery with Airflow (Cloud Composer), Dataflow, and Python loaders; model it in dbt; and deliver the analysis in Hex. No handoffs, no "that's not my layer." - Build for 10x. We're growing fast, and the data is growing with us. Every pipeline and model you ship should survive the volume multiplying in the next few months. Reliability, cost, and partition strategy are part of the design, not an afterthought. - Explain what's driving the numbers. When a metric moves, you find out why. You can trace a number from a Hex dashboard back through the dbt models to the raw source and tell the business what actually pushed it up or down. - Work AI-first, and own the output. You lean hard on modern AI tooling (coding agents, LLMs) to move faster across the whole stack, but you stay accountable for what lands in production. You know the difference between letting AI draft and letting AI decide, and you keep correctness, cost, and ownership in your own hands. This matters a lot to us. - Partner directly with business teams. You don't wait for tickets. You understand what growth, finance, and product are trying to learn, get ahead of it, and translate messy questions into models and answers they can trust. - Manage infrastructure as code. Provision and evolve the data platform with Pulumi, and treat the pipeline as a production system you're on the hook for. - Stay on the frontier. You actively track what's new in data engineering and AI, and you bring the good tools in instead of waiting for someone to tell you about them. YOU MIGHT BE A GOOD FIT IF YOU - Have 5+ years building and operating production data pipelines and warehouses - Are deep with our stack or close equivalents: GCP, BigQuery, dbt, Airflow, Dataflow, Metaplane, Hex, and infrastructure as code (Pulumi or Terraform) - Write strong SQL and can both build the pipeline and read the metric. You're an engineer who can do analysis, not one or the other - Already build AI into how you work day to day, and have a clear sense of where a human has to stay in the loop - Communicate clearly with non-technical stakeholders and chase down what they actually need - Are comfortable navigating ambiguity, moving quickly, and designing for scale from the start - Are genuinely passionate about data, with the track record to back it up WHAT WE OFFER - Fully Remote We hire globally. We believe you can do your best work from anywhere. There are no Supabase offices, but we provide a WeWork membership or co-working allowance you can use anywhere in the world. - ESOP Every team member receives ESOP (equity ownership) in the company. We want everyone to share in the upside of what we’re building together. - Tech Allowance Use this budget to set up your ideal work environment—laptop, monitor, headphones, or whatever helps you do your best work. - Health Benefits Supabase covers 100% of health insurance for employees and 80% for dependents, wherever you are. Your wellbeing and your family’s health are important to us. - Annual Off-Sites Once a year, the entire company gathers in a new city for a week of connection, collaboration, and fun. It’s a highlight of our year. - Flexible Work We operate asynchronously and trust you to manage your own time. You know what needs to be done and when. - Professional Development Every team member receives an annual education allowance to spend on learning—courses, books, conferences, or anything that supports your growth. ABOUT THE TEAM Supabase was born-remote and open-source-first. We believe our globally distributed team is our secret weapon in building tools developers love. - 280+ team members - 55+ countries - 20+ languages spoken - $500M raised - 500,000+ community members We move fast, build in public, and use what we ship. If it’s in your project, we probably use it in ours too. We believe deeply in the open-source ecosystem and strive to support—not replace—existing tools and communities. HIRING PROCESS We keep things simple, async-friendly, and respectful of your time: 1. Apply – Our team will review your application. 2. Intro Call – A short video chat to get to know each other. 3. Interviews – Up to four calls with: - Team Leads - Future teammates - Someone cross-functional from product, growth, or engineering (depending on the role) - Someone from our leadership/founding team 4. Decision – We may follow up with a final question or go straight to offer. All communication is remote and we aim to move fast. | M127: 0 | N127: =I127+J127 -> 1 | O127: {=OR(B127=Hist!$A$1:$A$85)} -> TRUE

Sheet Hist
A1: final_job_id
A2: greenhouse|figma|5220003004
A3: greenhouse|figma|5552580004
A4: greenhouse|figma|6013304004
A5: greenhouse|figma|6013303004
A6: greenhouse|figma|5551532004
A7: ashby|notion|a1216dba-e175-4a3d-b712-401c9fbdcd92
A8: ashby|notion|e4229ca4-8210-4282-98ed-2071478f72aa
A9: ashby|notion|6597b600-7781-46e6-b70a-a9af4fb2b61b
A10: greenhouse|stripe|7540441
A11: greenhouse|stripe|7612192
A12: greenhouse|stripe|8044686
... A85: ashby|supabase|44f6de1c-0fdc-4d46-aa3e-7d57b8be38b2
